Workbook

Sheet START HERE
A1: MICHAEL BID INTELLIGENCE PORTFOLIO | B1: MICHAEL BID INTELLIGENCE PORTFOLIO | C1: MICHAEL BID INTELLIGENCE PORTFOLIO | D1: MICHAEL BID INTELLIGENCE PORTFOLIO | E1: MICHAEL BID INTELLIGENCE PORTFOLIO | F1: MICHAEL BID INTELLIGENCE PORTFOLIO | G1: MICHAEL BID INTELLIGENCE PORTFOLIO | H1: MICHAEL BID INTELLIGENCE PORTFOLIO
A2: Interactive fictional bid-management and business-intelligence demonstration | Created for Michael Ngo | B2: Interactive fictional bid-management and business-intelligence demonstration | Created for Michael Ngo | C2: Interactive fictional bid-management and business-intelligence demonstration | Created for Michael Ngo | D2: Interactive fictional bid-management and business-intelligence demonstration | Created for Michael Ngo | E2: Interactive fictional bid-management and business-intelligence demonstration | Created for Michael Ngo | F2: Interactive fictional bid-management and business-intelligence demonstration | Created for Michael Ngo | G2: Interactive fictional bid-management and business-intelligence demonstration | Created for Michael Ngo | H2: Interactive fictional bid-management and business-intelligence demonstration | Created for Michael Ngo
A5: CONFIDENTIALITY NOTICE | B5: CONFIDENTIALITY NOTICE | C5: CONFIDENTIALITY NOTICE | D5: CONFIDENTIALITY NOTICE | E5: CONFIDENTIALITY NOTICE | F5: CONFIDENTIALITY NOTICE | G5: CONFIDENTIALITY NOTICE | H5: CONFIDENTIALITY NOTICE
A6: This workbook uses an entirely fictional dataset. Names, prices, opportunities, outcomes, contacts, and narratives were created as an original portfolio demonstration and do not reproduce employer data. | B6: This workbook uses an entirely fictional dataset. Names, prices, opportunities, outcomes, contacts, and narratives were created as an original portfolio demonstration and do not reproduce employer data. | C6: This workbook uses an entirely fictional dataset. Names, prices, opportunities, outcomes, contacts, and narratives were created as an original portfolio demonstration and do not reproduce employer data. | D6: This workbook uses an entirely fictional dataset. Names, prices, opportunities, outcomes, contacts, and narratives were created as an original portfolio demonstration and do not reproduce employer data. | E6: This workbook uses an entirely fictional dataset. Names, prices, opportunities, outcomes, contacts, and narratives were created as an original portfolio demonstration and do not reproduce employer data. | F6: This workbook uses an entirely fictional dataset. Names, prices, opportunities, outcomes, contacts, and narratives were created as an original portfolio demonstration and do not reproduce employer data. | G6: This workbook uses an entirely fictional dataset. Names, prices, opportunities, outcomes, contacts, and narratives were created as an original portfolio demonstration and do not reproduce employer data. | H6: This workbook uses an entirely fictional dataset. Names, prices, opportunities, outcomes, contacts, and narratives were created as an original portfolio demonstration and do not reproduce employer data.
A7: This workbook uses an entirely fictional dataset. Names, prices, opportunities, outcomes, contacts, and narratives were created as an original portfolio demonstration and do not reproduce employer data. | B7: This workbook uses an entirely fictional dataset. Names, prices, opportunities, outcomes, contacts, and narratives were created as an original portfolio demonstration and do not reproduce employer data. | C7: This workbook uses an entirely fictional dataset. Names, prices, opportunities, outcomes, contacts, and narratives were created as an original portfolio demonstration and do not reproduce employer data. | D7: This workbook uses an entirely fictional dataset. Names, prices, opportunities, outcomes, contacts, and narratives were created as an original portfolio demonstration and do not reproduce employer data. | E7: This workbook uses an entirely fictional dataset. Names, prices, opportunities, outcomes, contacts, and narratives were created as an original portfolio demonstration and do not reproduce employer data. | F7: This workbook uses an entirely fictional dataset. Names, prices, opportunities, outcomes, contacts, and narratives were created as an original portfolio demonstration and do not reproduce employer data. | G7: This workbook uses an entirely fictional dataset. Names, prices, opportunities, outcomes, contacts, and narratives were created as an original portfolio demonstration and do not reproduce employer data. | H7: This workbook uses an entirely fictional dataset. Names, prices, opportunities, outcomes, contacts, and narratives were created as an original portfolio demonstration and do not reproduce employer data.
A9: BUSINESS PROBLEM | B9: BUSINESS PROBLEM | C9: BUSINESS PROBLEM | D9: BUSINESS PROBLEM | E9: BUSINESS PROBLEM | F9: BUSINESS PROBLEM | G9: BUSINESS PROBLEM | H9: BUSINESS PROBLEM
A10: Opportunity information often arrives through disconnected portals, emails, documents, and internal conversations. Without a structured system, leadership cannot reliably measure workload, pursuit quality, bottlenecks, pricing performance, or decision outcomes. | B10: Opportunity information often arrives through disconnected portals, emails, documents, and internal conversations. Without a structured system, leadership cannot reliably measure workload, pursuit quality, bottlenecks, pricing performance, or decision outcomes. | C10: Opportunity information often arrives through disconnected portals, emails, documents, and internal conversations. Without a structured system, leadership cannot reliably measure workload, pursuit quality, bottlenecks, pricing performance, or decision outcomes. | D10: Opportunity information often arrives through disconnected portals, emails, documents, and internal conversations. Without a structured system, leadership cannot reliably measure workload, pursuit quality, bottlenecks, pricing performance, or decision outcomes. | E10: Opportunity information often arrives through disconnected portals, emails, documents, and internal conversations. Without a structured system, leadership cannot reliably measure workload, pursuit quality, bottlenecks, pricing performance, or decision outcomes. | F10: Opportunity information often arrives through disconnected portals, emails, documents, and internal conversations. Without a structured system, leadership cannot reliably measure workload, pursuit quality, bottlenecks, pricing performance, or decision outcomes. | G10: Opportunity information often arrives through disconnected portals, emails, documents, and internal conversations. Without a structured system, leadership cannot reliably measure workload, pursuit quality, bottlenecks, pricing performance, or decision outcomes. | H10: Opportunity information often arrives through disconnected portals, emails, documents, and internal conversations. Without a structured system, leadership cannot reliably measure workload, pursuit quality, bottlenecks, pricing performance, or decision outcomes.
A11: Opportunity information often arrives through disconnected portals, emails, documents, and internal conversations. Without a structured system, leadership cannot reliably measure workload, pursuit quality, bottlenecks, pricing performance, or decision outcomes. | B11: Opportunity information often arrives through disconnected portals, emails, documents, and internal conversations. Without a structured system, leadership cannot reliably measure workload, pursuit quality, bottlenecks, pricing performance, or decision outcomes. | C11: Opportunity information often arrives through disconnected portals, emails, documents, and internal conversations. Without a structured system, leadership cannot reliably measure workload, pursuit quality, bottlenecks, pricing performance, or decision outcomes. | D11: Opportunity information often arrives through disconnected portals, emails, documents, and internal conversations. Without a structured system, leadership cannot reliably measure workload, pursuit quality, bottlenecks, pricing performance, or decision outcomes. | E11: Opportunity information often arrives through disconnected portals, emails, documents, and internal conversations. Without a structured system, leadership cannot reliably measure workload, pursuit quality, bottlenecks, pricing performance, or decision outcomes. | F11: Opportunity information often arrives through disconnected portals, emails, documents, and internal conversations. Without a structured system, leadership cannot reliably measure workload, pursuit quality, bottlenecks, pricing performance, or decision outcomes. | G11: Opportunity information often arrives through disconnected portals, emails, documents, and internal conversations. Without a structured system, leadership cannot reliably measure workload, pursuit quality, bottlenecks, pricing performance, or decision outcomes. | H11: Opportunity information often arrives through disconnected portals, emails, documents, and internal conversations. Without a structured system, leadership cannot reliably measure workload, pursuit quality, bottlenecks, pricing performance, or decision outcomes.
A13: MY APPROACH | B13: MY APPROACH | C13: MY APPROACH | D13: MY APPROACH | E13: MY APPROACH | F13: MY APPROACH | G13: MY APPROACH | H13: MY APPROACH
A14: I designed a single-source bid register with controlled statuses, structured risk fields, workflow timing, bid/no-bid reasoning, submission tracking, and post-bid intelligence. Each analytical view is driven from that shared architecture. | B14: I designed a single-source bid register with controlled statuses, structured risk fields, workflow timing, bid/no-bid reasoning, submission tracking, and post-bid intelligence. Each analytical view is driven from that shared architecture. | C14: I designed a single-source bid register with controlled statuses, structured risk fields, workflow timing, bid/no-bid reasoning, submission tracking, and post-bid intelligence. Each analytical view is driven from that shared architecture. | D14: I designed a single-source bid register with controlled statuses, structured risk fields, workflow timing, bid/no-bid reasoning, submission tracking, and post-bid intelligence. Each analytical view is driven from that shared architecture. | E14: I designed a single-source bid register with controlled statuses, structured risk fields, workflow timing, bid/no-bid reasoning, submission tracking, and post-bid intelligence. Each analytical view is driven from that shared architecture. | F14: I designed a single-source bid register with controlled statuses, structured risk fields, workflow timing, bid/no-bid reasoning, submission tracking, and post-bid intelligence. Each analytical view is driven from that shared architecture. | G14: I designed a single-source bid register with controlled statuses, structured risk fields, workflow timing, bid/no-bid reasoning, submission tracking, and post-bid intelligence. Each analytical view is driven from that shared architecture. | H14: I designed a single-source bid register with controlled statuses, structured risk fields, workflow timing, bid/no-bid reasoning, submission tracking, and post-bid intelligence. Each analytical view is driven from that shared architecture.
A15: I designed a single-source bid register with controlled statuses, structured risk fields, workflow timing, bid/no-bid reasoning, submission tracking, and post-bid intelligence. Each analytical view is driven from that shared architecture. | B15: I designed a single-source bid register with controlled statuses, structured risk fields, workflow timing, bid/no-bid reasoning, submission tracking, and post-bid intelligence. Each analytical view is driven from that shared architecture. | C15: I designed a single-source bid register with controlled statuses, structured risk fields, workflow timing, bid/no-bid reasoning, submission tracking, and post-bid intelligence. Each analytical view is driven from that shared architecture. | D15: I designed a single-source bid register with controlled statuses, structured risk fields, workflow timing, bid/no-bid reasoning, submission tracking, and post-bid intelligence. Each analytical view is driven from that shared architecture. | E15: I designed a single-source bid register with controlled statuses, structured risk fields, workflow timing, bid/no-bid reasoning, submission tracking, and post-bid intelligence. Each analytical view is driven from that shared architecture. | F15: I designed a single-source bid register with controlled statuses, structured risk fields, workflow timing, bid/no-bid reasoning, submission tracking, and post-bid intelligence. Each analytical view is driven from that shared architecture. | G15: I designed a single-source bid register with controlled statuses, structured risk fields, workflow timing, bid/no-bid reasoning, submission tracking, and post-bid intelligence. Each analytical view is driven from that shared architecture. | H15: I designed a single-source bid register with controlled statuses, structured risk fields, workflow timing, bid/no-bid reasoning, submission tracking, and post-bid intelligence. Each analytical view is driven from that shared architecture.
A17: SOLUTION | B17: SOLUTION | C17: SOLUTION | D17: SOLUTION | E17: SOLUTION | F17: SOLUTION | G17: SOLUTION | H17: SOLUTION
... A32: Recommended navigation: Executive Dashboard → Active Pipeline → Bid-No-Bid Intelligence → Post-Bid Analysis → Workflow Intelligence → Opportunity Detail. Use the blue selector cells and Excel filters to interact with the model. | B32: Recommended navigation: Executive Dashboard → Active Pipeline → Bid-No-Bid Intelligence → Post-Bid Analysis → Workflow Intelligence → Opportunity Detail. Use the blue selector cells and Excel filters to interact with the model. | C32: Recommended navigation: Executive Dashboard → Active Pipeline → Bid-No-Bid Intelligence → Post-Bid Analysis → Workflow Intelligence → Opportunity Detail. Use the blue selector cells and Excel filters to interact with the model. | D32: Recommended navigation: Executive Dashboard → Active Pipeline → Bid-No-Bid Intelligence → Post-Bid Analysis → Workflow Intelligence → Opportunity Detail. Use the blue selector cells and Excel filters to interact with the model. | E32: Recommended navigation: Executive Dashboard → Active Pipeline → Bid-No-Bid Intelligence → Post-Bid Analysis → Workflow Intelligence → Opportunity Detail. Use the blue selector cells and Excel filters to interact with the model. | F32: Recommended navigation: Executive Dashboard → Active Pipeline → Bid-No-Bid Intelligence → Post-Bid Analysis → Workflow Intelligence → Opportunity Detail. Use the blue selector cells and Excel filters to interact with the model. | G32: Recommended navigation: Executive Dashboard → Active Pipeline → Bid-No-Bid Intelligence → Post-Bid Analysis → Workflow Intelligence → Opportunity Detail. Use the blue selector cells and Excel filters to interact with the model. | H32: Recommended navigation: Executive Dashboard → Active Pipeline → Bid-No-Bid Intelligence → Post-Bid Analysis → Workflow Intelligence → Opportunity Detail. Use the blue selector cells and Excel filters to interact with the model.

Sheet 1. Opportunity Register
A1: Opportunity ID | B1: Opportunity | C1: Client | D1: Client Type | E1: Service | F1: Market | G1: Owner | H1: Identified Date | I1: Due Date | J1: Current Stage | K1: Outcome | L1: Approved Pursuit? | M1: Submitted? | N1: Est. Annual Value | O1: Est. Total Value | P1: Square Feet | Q1: Site Count | R1: Term (Months) | S1: Prevailing Wage? | T1: Bond Required? | U1: Risk Level | V1: No-Bid Reason | W1: Decision Notes | X1: Submitted Price | Y1: Winning Price | Z1: Winner | AA1: Incumbent | AB1: Review Days | AC1: Operational Review Days | AD1: Pricing Days | AE1: Proposal Days | AF1: Decision Date | AG1: Submitted Date | AH1: Award Date | AI1: Variance $ | AJ1: Variance % | AK1: Price / SF | AL1: Days to Decision | AM1: Proposal Turnaround | AN1: Next Action | AO1: Key Finding | AP1: Reporting Month
A2: BID-001 | B2: Daily Bugle Headquarters – Integrated Facility Operations | C2: Daily Bugle Headquarters | D2: Commercial | E2: Facility Maintenance | F2: Outer Region | G2: Michael Ngo | H2: 45902 | I2: 45920 | J2: Closed – No-Bid | K2: No-Bid | L2: No | M2: No | N2: 62400 | O2: 62400 | P2: 12000 | Q2: 1 | R2: 12 | S2: No | T2: No | U2: High | V2: Geographic Distance | W2: Declined because geographic distance reduced strategic or operational fit. | AA2: Atlas Building Partners | AB2: 1 | AC2: 7 | AD2: 0 | AE2: 0 | AF2: 45910 | AI2: =IF(OR(X2="",Y2=""),"",X2-Y2) | AJ2: =IFERROR((X2-Y2)/Y2,"") | AK2: =IFERROR(X2/P2,"") -> 0 | AL2: =IF(AF2="","",AF2-H2) -> 8 | AM2: =IF(AG2="","",AG2-AF2) | AN2: Document decision intelligence | AO2: Resources were preserved for better-aligned pursuits. | AP2: Sep 2025
A3: BID-002 | B3: Metropolis Community College – Districtwide Pest Prevention | C3: Metropolis Community College | D3: Education | E3: Pest Control | F3: Hudson Valley | G3: Avery Chen | H3: 45903 | I3: 45922 | J3: Closed – Awarded | K3: Lost | L3: Yes | M3: Yes | N3: 18000 | O3: 36000 | Q3: 8 | R3: 24 | S3: Yes | T3: No | U3: Low | W3: Pursuit aligned with the fictional bidder's service strategy; routine pursuit within demonstrated service and geographic capabilities. | X3: 36000 | Y3: 33000 | Z3: Wayne Municipal Services | AA3: Blue Lantern Services | AB3: 2 | AC3: 3 | AD3: 3 | AE3: 3 | AF3: 45908 | AG3: 45914 | AH3: 45941 | AI3: =IF(OR(X3="",Y3=""),"",X3-Y3) -> 3000 | AJ3: =IFERROR((X3-Y3)/Y3,"") -> 0.090909091 | AK3: =IFERROR(X3/P3,"") | AL3: =IF(AF3="","",AF3-H3) -> 5 | AM3: =IF(AG3="","",AG3-AF3) -> 6 | AN3: Request debrief or tabulation | AO3: Result provides a usable market benchmark for future pricing. | AP3: Sep 2025
A4: BID-003 | B4: Atlas County Services – Multi-Phase Final Clean | C4: Atlas County Services | D4: Government | E4: Post-Construction Cleaning | F4: Outer Region | G4: Jordan Ellis | H4: 45904 | I4: 45924 | J4: Closed – No-Bid | K4: No-Bid | L4: No | M4: No | N4: 68500 | O4: 205500 | P4: 87862 | Q4: 1 | R4: 36 | S4: Yes | T4: No | U4: Medium | V4: Geographic Distance | W4: Declined because geographic distance reduced strategic or operational fit. | AA4: Sentinel Operations | AB4: 3 | AC4: 4 | AD4: 0 | AE4: 0 | AF4: 45911 | AI4: =IF(OR(X4="",Y4=""),"",X4-Y4) | AJ4: =IFERROR((X4-Y4)/Y4,"") | AK4: =IFERROR(X4/P4,"") -> 0 | AL4: =IF(AF4="","",AF4-H4) -> 7 | AM4: =IF(AG4="","",AG4-AF4) | AN4: Document decision intelligence | AO4: Resources were preserved for better-aligned pursuits. | AP4: Sep 2025
A5: BID-004 | B5: Orbit Retail Properties – Municipal Buildings Custodial Services | C5: Orbit Retail Properties | D5: Commercial | E5: Custodial | F5: North Jersey | G5: Priya Shah | H5: 45905 | I5: 45926 | J5: Closed – Awarded | K5: Lost | L5: Yes | M5: Yes | N5: 320800 | O5: 320800 | P5: 125793 | Q5: 8 | R5: 12 | S5: No | T5: No | U5: Low | W5: Pursuit aligned with the fictional bidder's service strategy; routine pursuit within demonstrated service and geographic capabilities. | X5: 320800 | Y5: 286400 | Z5: Blue Lantern Services | AA5: Pinnacle Facility Care | AB5: 1 | AC5: 5 | AD5: 5 | AE5: 2 | AF5: 45911 | AG5: 45918 | AH5: 45947 | AI5: =IF(OR(X5="",Y5=""),"",X5-Y5) -> 34400 | AJ5: =IFERROR((X5-Y5)/Y5,"") -> 0.12011173 | AK5: =IFERROR(X5/P5,"") -> 2.5502214 | AL5: =IF(AF5="","",AF5-H5) -> 6 | AM5: =IF(AG5="","",AG5-AF5) -> 7 | AN5: Request debrief or tabulation | AO5: Result provides a usable market benchmark for future pricing. | AP5: Sep 2025
A6: BID-005 | B6: Stark Facilities Group – Grounds and Landscape Maintenance | C6: Stark Facilities Group | D6: Commercial | E6: Landscaping | F6: Central Jersey | G6: Michael Ngo | H6: 45906 | I6: 45928 | J6: Closed – No-Bid | K6: No-Bid | L6: No | M6: No | N6: 75300 | O6: 150600 | P6: 163724 | Q6: 1 | R6: 24 | S6: No | T6: No | U6: Low | V6: Insufficient Time | W6: Declined because insufficient time reduced strategic or operational fit. | AA6: Stark Facilities Group | AB6: 2 | AC6: 2 | AD6: 0 | AE6: 0 | AF6: 45910 | AI6: =IF(OR(X6="",Y6=""),"",X6-Y6) | AJ6: =IFERROR((X6-Y6)/Y6,"") | AK6: =IFERROR(X6/P6,"") -> 0 | AL6: =IF(AF6="","",AF6-H6) -> 4 | AM6: =IF(AG6="","",AG6-AF6) | AN6: Document decision intelligence | AO6: Resources were preserved for better-aligned pursuits. | AP6: Sep 2025
A7: BID-006 | B7: Atlas County Services – Multi-Site Evening Janitorial | C7: Atlas County Services | D7: Government | E7: Janitorial | F7: North Jersey | G7: Avery Chen | H7: 45937 | I7: 45960 | J7: Closed – Awarded | K7: Lost | L7: Yes | M7: Yes | N7: 453700 | O7: 1361100 | P7: 201655 | Q7: 8 | R7: 36 | S7: Yes | T7: Yes | U7: Low | W7: Pursuit aligned with the fictional bidder's service strategy; routine pursuit within demonstrated service and geographic capabilities. | X7: 1361100 | Y7: 1266100 | Z7: Pinnacle Facility Care | AA7: Wayne Municipal Services | AB7: 3 | AC7: 3 | AD7: 3 | AE7: 4 | AF7: 45943 | AG7: 45950 | AH7: 45983 | AI7: =IF(OR(X7="",Y7=""),"",X7-Y7) -> 95000 | AJ7: =IFERROR((X7-Y7)/Y7,"") -> 0.075033568 | AK7: =IFERROR(X7/P7,"") -> 6.7496467 | AL7: =IF(AF7="","",AF7-H7) -> 6 | AM7: =IF(AG7="","",AG7-AF7) -> 7 | AN7: Request debrief or tabulation | AO7: Result provides a usable market benchmark for future pricing. | AP7: Oct 2025
A8: BID-007 | B8: Orbit Retail Properties – Rodent Control Program | C8: Orbit Retail Properties | D8: Commercial | E8: Pest Control | F8: Central Jersey | G8: Jordan Ellis | H8: 45938 | I8: 45962 | J8: Closed – Awarded | K8: Lost | L8: Yes | M8: Yes | N8: 18000 | O8: 18000 | Q8: 1 | R8: 12 | S8: No | T8: No | U8: Low | W8: Pursuit aligned with the fictional bidder's service strategy; routine pursuit within demonstrated service and geographic capabilities. | X8: 18000 | Y8: 16500 | Z8: Stark Facilities Group | AA8: Atlas Building Partners | AB8: 1 | AC8: 4 | AD8: 4 | AE8: 2 | AF8: 45943 | AG8: 45949 | AH8: 45986 | AI8: =IF(OR(X8="",Y8=""),"",X8-Y8) -> 1500 | AJ8: =IFERROR((X8-Y8)/Y8,"") -> 0.090909091 | AK8: =IFERROR(X8/P8,"") | AL8: =IF(AF8="","",AF8-H8) -> 5 | AM8: =IF(AG8="","",AG8-AF8) -> 6 | AN8: Request debrief or tabulation | AO8: Result provides a usable market benchmark for future pricing. | AP8: Oct 2025
A9: BID-008 | B9: Stark Facilities Group – New Facility Turnover Cleaning | C9: Stark Facilities Group | D9: Commercial | E9: Post-Construction Cleaning | F9: Metro NY | G9: Priya Shah | H9: 45939 | I9: 45964 | J9: Closed – Awarded | K9: Lost | L9: Yes | M9: Yes | N9: 216500 | O9: 433000 | P9: 277517 | Q9: 8 | R9: 24 | S9: No | T9: No | U9: Low | W9: Pursuit aligned with the fictional bidder's service strategy; routine pursuit within demonstrated service and geographic capabilities. | X9: 433000 | Y9: 391900 | Z9: Wayne Municipal Services | AA9: Blue Lantern Services | AB9: 2 | AC9: 5 | AD9: 5 | AE9: 3 | AF9: 45946 | AG9: 45954 | AH9: 45989 | AI9: =IF(OR(X9="",Y9=""),"",X9-Y9) -> 41100 | AJ9: =IFERROR((X9-Y9)/Y9,"") -> 0.10487369 | AK9: =IFERROR(X9/P9,"") -> 1.5602648 | AL9: =IF(AF9="","",AF9-H9) -> 7 | AM9: =IF(AG9="","",AG9-AF9) -> 8 | AN9: Request debrief or tabulation | AO9: Result provides a usable market benchmark for future pricing. | AP9: Oct 2025
A10: BID-009 | B10: Parker Research Campus – Campus Custodial Services | C10: Parker Research Campus | D10: Commercial | E10: Custodial | F10: Hudson Valley | G10: Michael Ngo | H10: 45940 | I10: 45966 | J10: Closed – No-Bid | K10: No-Bid | L10: No | M10: No | N10: 804400 | O10: 2413200 | P10: 315448 | Q10: 1 | R10: 36 | S10: No | T10: No | U10: Low | V10: Scope Misalignment | W10: Declined because scope misalignment reduced strategic or operational fit. | AA10: Sentinel Operations | AB10: 3 | AC10: 2 | AD10: 0 | AE10: 0 | AF10: 45945 | AI10: =IF(OR(X10="",Y10=""),"",X10-Y10) | AJ10: =IFERROR((X10-Y10)/Y10,"") | AK10: =IFERROR(X10/P10,"") -> 0 | AL10: =IF(AF10="","",AF10-H10) -> 5 | AM10: =IF(AG10="","",AG10-AF10) | AN10: Document decision intelligence | AO10: Resources were preserved for better-aligned pursuits. | AP10: Oct 2025
A11: BID-010 | B11: Beacon Preparatory Schools – Seasonal Grounds Services | C11: Beacon Preparatory Schools | D11: Education | E11: Landscaping | F11: Outer Region | G11: Avery Chen | H11: 45941 | I11: 45968 | J11: Closed – No-Bid | K11: No-Bid | L11: No | M11: No | N11: 162600 | O11: 162600 | P11: 353379 | Q11: 8 | R11: 12 | S11: No | T11: No | U11: Medium | V11: Geographic Distance | W11: Declined because geographic distance reduced strategic or operational fit. | AA11: Pinnacle Facility Care | AB11: 1 | AC11: 3 | AD11: 0 | AE11: 0 | AF11: 45945 | AI11: =IF(OR(X11="",Y11=""),"",X11-Y11) | AJ11: =IFERROR((X11-Y11)/Y11,"") | AK11: =IFERROR(X11/P11,"") -> 0 | AL11: =IF(AF11="","",AF11-H11) -> 4 | AM11: =IF(AG11="","",AG11-AF11) | AN11: Document decision intelligence | AO11: Resources were preserved for better-aligned pursuits. | AP11: Oct 2025
A12: BID-011 | B12: Stark Facilities Group – Event Security Coverage | C12: Stark Facilities Group | D12: Commercial | E12: Security | F12: Hudson Valley | G12: Jordan Ellis | H12: 45973 | I12: 46001 | J12: Closed – Awarded | K12: Lost | L12: Yes | M12: Yes | N12: 170500 | O12: 341000 | Q12: 1 | R12: 24 | S12: No | T12: No | U12: High | W12: Pursuit aligned with the fictional bidder's service strategy; requires leadership review of operating model, compliance exposure, and staffing assumptions. | X12: 341000 | Y12: 289000 | Z12: Sentinel Operations | AA12: Stark Facilities Group | AB12: 2 | AC12: 7 | AD12: 4 | AE12: 3 | AF12: 45982 | AG12: 45989 | AH12: 46029 | AI12: =IF(OR(X12="",Y12=""),"",X12-Y12) -> 52000 | AJ12: =IFERROR((X12-Y12)/Y12,"") -> 0.1799308 | AK12: =IFERROR(X12/P12,"") | AL12: =IF(AF12="","",AF12-H12) -> 9 | AM12: =IF(AG12="","",AG12-AF12) -> 7 | AN12: Request debrief or tabulation | AO12: Result provides a usable market benchmark for future pricing. | AP12: Nov 2025
A13: BID-012 | B13: Parker Research Campus – Carpet and Floor Renewal | C13: Parker Research Campus | D13: Commercial | E13: Specialty Floor Care | F13: Outer Region | G13: Priya Shah | H13: 45974 | I13: 46003 | J13: Closed – No-Bid | K13: No-Bid | L13: No | M13: No | N13: 145900 | O13: 437700 | P13: 429241 | Q13: 8 | R13: 36 | S13: No | T13: No | U13: Medium | V13: Geographic Distance | W13: Declined because geographic distance reduced strategic or operational fit. | AA13: Wayne Municipal Services | AB13: 3 | AC13: 5 | AD13: 0 | AE13: 0 | AF13: 45982 | AI13: =IF(OR(X13="",Y13=""),"",X13-Y13) | AJ13: =IFERROR((X13-Y13)/Y13,"") | AK13: =IFERROR(X13/P13,"") -> 0 | AL13: =IF(AF13="","",AF13-H13) -> 8 | AM13: =IF(AG13="","",AG13-AF13) | AN13: Document decision intelligence | AO13: Resources were preserved for better-aligned pursuits. | AP13: Nov 2025
A14: BID-013 | B14: Beacon Preparatory Schools – Final Construction Cleaning | C14: Beacon Preparatory Schools | D14: Education | E14: Post-Construction Cleaning | F14: North Jersey | G14: Michael Ngo | H14: 45975 | I14: 46005 | J14: Closed – No-Bid | K14: No-Bid | L14: No | M14: No | N14: 364400 | O14: 364400 | P14: 467172 | Q14: 1 | R14: 12 | S14: No | T14: No | U14: Low | V14: Geographic Distance | W14: Declined because geographic distance reduced strategic or operational fit. | AA14: Atlas Building Partners | AB14: 1 | AC14: 2 | AD14: 0 | AE14: 0 | AF14: 45978 | AI14: =IF(OR(X14="",Y14=""),"",X14-Y14) | AJ14: =IFERROR((X14-Y14)/Y14,"") | AK14: =IFERROR(X14/P14,"") -> 0 | AL14: =IF(AF14="","",AF14-H14) -> 3 | AM14: =IF(AG14="","",AG14-AF14) | AN14: Document decision intelligence | AO14: Resources were preserved for better-aligned pursuits. | AP14: Nov 2025
A15: BID-014 | B15: Wayne Municipal Services – Technical Building Maintenance | C15: Wayne Municipal Services | D15: Government | E15: Facility Maintenance | F15: Central Jersey | G15: Avery Chen | H15: 45976 | I15: 46007 | J15: Closed – Awarded | K15: Lost | L15: Yes | M15: Yes | N15: 2626500 | O15: 5253000 | P15: 505103 | Q15: 8 | R15: 24 | S15: Yes | T15: Yes | U15: High | W15: Pursuit aligned with the fictional bidder's service strategy; requires leadership review of operating model, compliance exposure, and staffing assumptions. | X15: 5253000 | Y15: 4169000 | Z15: Wayne Municipal Services | AA15: Blue Lantern Services | AB15: 2 | AC15: 8 | AD15: 3 | AE15: 3 | AF15: 45986 | AG15: 45992 | AH15: 46038 | AI15: =IF(OR(X15="",Y15=""),"",X15-Y15) -> 1084000 | AJ15: =IFERROR((X15-Y15)/Y15,"") -> 0.26001439 | AK15: =IFERROR(X15/P15,"") -> 10.399859 | AL15: =IF(AF15="","",AF15-H15) -> 10 | AM15: =IF(AG15="","",AG15-AF15) -> 6 | AN15: Request debrief or tabulation | AO15: Price exceeded the market benchmark, suggesting conservative staffing or risk assumptions. | AP15: Nov 2025
A16: BID-015 | B16: Emerald City Administrative Center – Campus Landscape Program | C16: Emerald City Administrative Center | D16: Government | E16: Landscaping | F16: Metro NY | G16: Jordan Ellis | H16: 45977 | I16: 46009 | J16: Closed – Awarded | K16: Lost | L16: Yes | M16: Yes | N16: 249800 | O16: 749400 | P16: 543034 | Q16: 1 | R16: 36 | S16: Yes | T16: No | U16: Low | W16: Pursuit aligned with the fictional bidder's service strategy; routine pursuit within demonstrated service and geographic capabilities. | X16: 749400 | Y16: 657400 | Z16: Atlas Building Partners | AA16: Sentinel Operations | AB16: 3 | AC16: 4 | AD16: 4 | AE16: 4 | AF16: 45984 | AG16: 45992 | AH16: 46041 | AI16: =IF(OR(X16="",Y16=""),"",X16-Y16) -> 92000 | AJ16: =IFERROR((X16-Y16)/Y16,"") -> 0.13994524 | AK16: =IFERROR(X16/P16,"") -> 1.3800241 | AL16: =IF(AF16="","",AF16-H16) -> 7 | AM16: =IF(AG16="","",AG16-AF16) -> 8 | AN16: Request debrief or tabulation | AO16: Result provides a usable market benchmark for future pricing. | AP16: Nov 2025
A17: BID-016 | B17: Beacon Preparatory Schools – Public Offices Custodial Support | C17: Beacon Preparatory Schools | D17: Education | E17: Janitorial | F17: Central Jersey | G17: Priya Shah | H17: 46008 | I17: 46041 | J17: Closed – Awarded | K17: Lost | L17: Yes | M17: Yes | N17: 1307200 | O17: 1307200 | P17: 580965 | Q17: 8 | R17: 12 | S17: No | T17: Yes | U17: High | W17: Pursuit aligned with the fictional bidder's service strategy; requires leadership review of operating model, compliance exposure, and staffing assumptions. | X17: 1307200 | Y17: 1216000 | Z17: Blue Lantern Services | AA17: Pinnacle Facility Care | AB17: 1 | AC17: 5 | AD17: 5 | AE17: 2 | AF17: 46014 | AG17: 46021 | AH17: 46074 | AI17: =IF(OR(X17="",Y17=""),"",X17-Y17) -> 91200 | AJ17: =IFERROR((X17-Y17)/Y17,"") -> 0.075 | AK17: =IFERROR(X17/P17,"") -> 2.2500495 | AL17: =IF(AF17="","",AF17-H17) -> 6 | AM17: =IF(AG17="","",AG17-AF17) -> 7 | AN17: Request debrief or tabulation | AO17: Result provides a usable market benchmark for future pricing. | AP17: Dec 2025
A18: BID-017 | B18: Wayne Municipal Services – Integrated Pest Management | C18: Wayne Municipal Services | D18: Government | E18: Pest Control | F18: Metro NY | G18: Michael Ngo | H18: 46009 | I18: 46043 | J18: Closed – No-Bid | K18: No-Bid | L18: No | M18: No | N18: 18000 | O18: 36000 | Q18: 1 | R18: 24 | S18: Yes | T18: No | U18: Low | V18: Minimum Qualifications | W18: Declined because minimum qualifications reduced strategic or operational fit. | AA18: Stark Facilities Group | AB18: 2 | AC18: 2 | AD18: 0 | AE18: 0 | AF18: 46013 | AI18: =IF(OR(X18="",Y18=""),"",X18-Y18) | AJ18: =IFERROR((X18-Y18)/Y18,"") | AK18: =IFERROR(X18/P18,"") | AL18: =IF(AF18="","",AF18-H18) -> 4 | AM18: =IF(AG18="","",AG18-AF18) | AN18: Document decision intelligence | AO18: Resources were preserved for better-aligned pursuits. | AP18: Dec 2025
A19: BID-018 | B19: Emerald City Administrative Center – Renovation Closeout Cleaning | C19: Emerald City Administrative Center | D19: Government | E19: Post-Construction Cleaning | F19: Hudson Valley | G19: Avery Chen | H19: 46010 | I19: 46045 | J19: Closed – Awarded | K19: Lost | L19: Yes | M19: Yes | N19: 512300 | O19: 1536900 | P19: 656827 | Q19: 8 | R19: 36 | S19: Yes | T19: Yes | U19: Low | W19: Pursuit aligned with the fictional bidder's service strategy; routine pursuit within demonstrated service and geographic capabilities. | X19: 1536900 | Y19: 1390900 | Z19: Pinnacle Facility Care | AA19: Wayne Municipal Services | AB19: 3 | AC19: 3 | AD19: 3 | AE19: 4 | AF19: 46016 | AG19: 46023 | AH19: 46080 | AI19: =IF(OR(X19="",Y19=""),"",X19-Y19) -> 146000 | AJ19: =IFERROR((X19-Y19)/Y19,"") -> 0.10496801 | AK19: =IFERROR(X19/P19,"") -> 2.3398855 | AL19: =IF(AF19="","",AF19-H19) -> 6 | AM19: =IF(AG19="","",AG19-AF19) -> 7 | AN19: Request debrief or tabulation | AO19: Result provides a usable market benchmark for future pricing. | AP19: Dec 2025
A20: BID-019 | B20: Keystone Civic Complex – Civic Center Custodial Program | C20: Keystone Civic Complex | D20: Government | E20: Custodial | F20: Outer Region | G20: Jordan Ellis | H20: 45993 | I20: 46029 | J20: Closed – No-Bid | K20: No-Bid | L20: No | M20: No | N20: 1771600 | O20: 1771600 | P20: 694758 | Q20: 1 | R20: 12 | S20: No | T20: Yes | U20: High | V20: Geographic Distance | W20: Declined because geographic distance reduced strategic or operational fit. | AA20: Atlas Building Partners | AB20: 1 | AC20: 4 | AD20: 0 | AE20: 0 | AF20: 45998 | AI20: =IF(OR(X20="",Y20=""),"",X20-Y20) | AJ20: =IFERROR((X20-Y20)/Y20,"") | AK20: =IFERROR(X20/P20,"") -> 0 | AL20: =IF(AF20="","",AF20-H20) -> 5 | AM20: =IF(AG20="","",AG20-AF20) | AN20: Document decision intelligence | AO20: Resources were preserved for better-aligned pursuits. | AP20: Dec 2025
A21: BID-020 | B21: Gotham Public Schools – Municipal Grounds Care | C21: Gotham Public Schools | D21: Education | E21: Landscaping | F21: North Jersey | G21: Priya Shah | H21: 45994 | I21: 46031 | J21: Closed – Awarded | K21: Lost | L21: Yes | M21: Yes | N21: 337000 | O21: 674000 | P21: 732689 | Q21: 8 | R21: 24 | S21: Yes | T21: No | U21: Low | W21: Pursuit aligned with the fictional bidder's service strategy; routine pursuit within demonstrated service and geographic capabilities. | X21: 674000 | Y21: 591200 | Z21: Wayne Municipal Services | AA21: Blue Lantern Services | AB21: 2 | AC21: 5 | AD21: 5 | AE21: 3 | AF21: 46001 | AG21: 46009 | AH21: 46068 | AI21: =IF(OR(X21="",Y21=""),"",X21-Y21) -> 82800 | AJ21: =IFERROR((X21-Y21)/Y21,"") -> 0.14005413 | AK21: =IFERROR(X21/P21,"") -> 0.91989917 | AL21: =IF(AF21="","",AF21-H21) -> 7 | AM21: =IF(AG21="","",AG21-AF21) -> 8 | AN21: Request debrief or tabulation | AO21: Result provides a usable market benchmark for future pricing. | AP21: Dec 2025
A22: BID-021 | B22: Emerald City Administrative Center – Unarmed Guard Services | C22: Emerald City Administrative Center | D22: Government | E22: Security | F22: Outer Region | G22: Michael Ngo | H22: 46026 | I22: 46044 | J22: Closed – No-Bid | K22: No-Bid | L22: No | M22: No | N22: 170500 | O22: 511500 | Q22: 1 | R22: 36 | S22: Yes | T22: No | U22: High | V22: Geographic Distance | W22: Declined because geographic distance reduced strategic or operational fit. | AA22: Sentinel Operations | AB22: 3 | AC22: 8 | AD22: 0 | AE22: 0 | AF22: 46037 | AI22: =IF(OR(X22="",Y22=""),"",X22-Y22) | AJ22: =IFERROR((X22-Y22)/Y22,"") | AK22: =IFERROR(X22/P22,"") | AL22: =IF(AF22="","",AF22-H22) -> 11 | AM22: =IF(AG22="","",AG22-AF22) | AN22: Document decision intelligence | AO22: Resources were preserved for better-aligned pursuits. | AP22: Jan 2026
A23: BID-022 | B23: Keystone Civic Complex – Districtwide Pest Prevention | C23: Keystone Civic Complex | D23: Government | E23: Pest Control | F23: North Jersey | G23: Avery Chen | H23: 46027 | I23: 46046 | J23: Closed – Awarded | K23: Lost | L23: Yes | M23: Yes | N23: 18000 | O23: 18000 | Q23: 8 | R23: 12 | S23: No | T23: No | U23: Low | W23: Pursuit aligned with the fictional bidder's service strategy; routine pursuit within demonstrated service and geographic capabilities. | X23: 18000 | Y23: 16500 | Z23: Blue Lantern Services | AA23: Pinnacle Facility Care | AB23: 1 | AC23: 3 | AD23: 3 | AE23: 2 | AF23: 46031 | AG23: 46036 | AH23: 46085 | AI23: =IF(OR(X23="",Y23=""),"",X23-Y23) -> 1500 | AJ23: =IFERROR((X23-Y23)/Y23,"") -> 0.090909091 | AK23: =IFERROR(X23/P23,"") | AL23: =IF(AF23="","",AF23-H23) -> 4 | AM23: =IF(AG23="","",AG23-AF23) -> 5 | AN23: Request debrief or tabulation | AO23: Result provides a usable market benchmark for future pricing. | AP23: Jan 2026
A24: BID-023 | B24: Gotham Public Schools – Districtwide Floor Services | C24: Gotham Public Schools | D24: Education | E24: Specialty Floor Care | F24: Central Jersey | G24: Jordan Ellis | H24: 46028 | I24: 46048 | J24: Closed – Awarded | K24: Won | L24: Yes | M24: Yes | N24: 287800 | O24: 575600 | P24: 846482 | Q24: 1 | R24: 24 | S24: Yes | T24: No | U24: Low | W24: Pursuit aligned with the fictional bidder's service strategy; routine pursuit within demonstrated service and geographic capabilities. | X24: 575600 | Y24: 575600 | Z24: Michael BidWorks | AA24: Stark Facilities Group | AB24: 2 | AC24: 4 | AD24: 4 | AE24: 3 | AF24: 46034 | AG24: 46041 | AH24: 46088 | AI24: =IF(OR(X24="",Y24=""),"",X24-Y24) -> 0 | AJ24: =IFERROR((X24-Y24)/Y24,"") -> 0 | AK24: =IFERROR(X24/P24,"") -> 0.67999083 | AL24: =IF(AF24="","",AF24-H24) -> 6 | AM24: =IF(AG24="","",AG24-AF24) -> 7 | AN24: Prepare transition brief | AO24: Competitive positioning and scope fit supported award. | AP24: Jan 2026
A25: BID-024 | B25: Northstar Charter Network – Municipal Buildings Custodial Services | C25: Northstar Charter Network | D25: Education | E25: Custodial | F25: Metro NY | G25: Priya Shah | H25: 46029 | I25: 46050 | J25: Closed – Awarded | K25: Lost | L25: Yes | M25: Yes | N25: 2255300 | O25: 6765900 | P25: 884413 | Q25: 8 | R25: 36 | S25: Yes | T25: Yes | U25: High | W25: Pursuit aligned with the fictional bidder's service strategy; requires leadership review of operating model, compliance exposure, and staffing assumptions. | X25: 6765900 | Y25: 6041000 | Z25: Pinnacle Facility Care | AA25: Wayne Municipal Services | AB25: 3 | AC25: 5 | AD25: 5 | AE25: 4 | AF25: 46037 | AG25: 46046 | AH25: 46091 | AI25: =IF(OR(X25="",Y25=""),"",X25-Y25) -> 724900 | AJ25: =IFERROR((X25-Y25)/Y25,"") -> 0.11999669 | AK25: =IFERROR(X25/P25,"") -> 7.6501589 | AL25: =IF(AF25="","",AF25-H25) -> 8 | AM25: =IF(AG25="","",AG25-AF25) -> 9 | AN25: Request debrief or tabulation | AO25: Result provides a usable market benchmark for future pricing. | AP25: Jan 2026
A26: BID-025 | B26: Harborlight Medical Offices – Grounds and Landscape Maintenance | C26: Harborlight Medical Offices | D26: Commercial | E26: Landscaping | F26: Hudson Valley | G26: Michael Ngo | H26: 46030 | I26: 46052 | J26: Closed – No-Bid | K26: No-Bid | L26: No | M26: No | N26: 18000 | O26: 18000 | P26: 32344 | Q26: 1 | R26: 12 | S26: No | T26: No | U26: Low | V26: Geographic Distance | W26: Declined because geographic distance reduced strategic or operational fit. | AA26: Atlas Building Partners | AB26: 1 | AC26: 2 | AD26: 0 | AE26: 0 | AF26: 46033 | AI26: =IF(OR(X26="",Y26=""),"",X26-Y26) | AJ26: =IFERROR((X26-Y26)/Y26,"") | AK26: =IFERROR(X26/P26,"") -> 0 | AL26: =IF(AF26="","",AF26-H26) -> 3 | AM26: =IF(AG26="","",AG26-AF26) | AN26: Document decision intelligence | AO26: Resources were preserved for better-aligned pursuits. | AP26: Jan 2026
A27: BID-026 | B27: Gotham Public Schools – Multi-Site Evening Janitorial | C27: Gotham Public Schools | D27: Education | E27: Janitorial | F27: Metro NY | G27: Avery Chen | H27: 46062 | I27: 46085 | J27: Closed – Awarded | K27: Won | L27: Yes | M27: Yes | N27: 158100 | O27: 316200 | P27: 70275 | Q27: 8 | R27: 24 | S27: Yes | T27: No | U27: Low | W27: Pursuit aligned with the fictional bidder's service strategy; routine pursuit within demonstrated service and geographic capabilities. | X27: 316200 | Y27: 316200 | Z27: Michael BidWorks | AA27: Blue Lantern Services | AB27: 2 | AC27: 3 | AD27: 3 | AE27: 3 | AF27: 46067 | AG27: 46073 | AH27: 46128 | AI27: =IF(OR(X27="",Y27=""),"",X27-Y27) -> 0 | AJ27: =IFERROR((X27-Y27)/Y27,"") -> 0 | AK27: =IFERROR(X27/P27,"") -> 4.4994664 | AL27: =IF(AF27="","",AF27-H27) -> 5 | AM27: =IF(AG27="","",AG27-AF27) -> 6 | AN27: Prepare transition brief | AO27: Competitive positioning and scope fit supported award. | AP27: Feb 2026
A28: BID-027 | B28: Northstar Charter Network – Multi-Site Facility Services | C28: Northstar Charter Network | D28: Education | E28: Facility Maintenance | F28: Hudson Valley | G28: Jordan Ellis | H28: 46063 | I28: 46087 | J28: Closed – Awarded | K28: Lost | L28: Yes | M28: Yes | N28: 562700 | O28: 1688100 | P28: 108206 | Q28: 1 | R28: 36 | S28: Yes | T28: Yes | U28: High | W28: Pursuit aligned with the fictional bidder's service strategy; requires leadership review of operating model, compliance exposure, and staffing assumptions. | X28: 1688100 | Y28: 1339800 | Z28: Atlas Building Partners | AA28: Sentinel Operations | AB28: 3 | AC28: 9 | AD28: 4 | AE28: 4 | AF28: 46075 | AG28: 46083 | AH28: 46131 | AI28: =IF(OR(X28="",Y28=""),"",X28-Y28) -> 348300 | AJ28: =IFERROR((X28-Y28)/Y28,"") -> 0.25996417 | AK28: =IFERROR(X28/P28,"") -> 15.600798 | AL28: =IF(AF28="","",AF28-H28) -> 12 | AM28: =IF(AG28="","",AG28-AF28) -> 8 | AN28: Request debrief or tabulation | AO28: Price exceeded the market benchmark, suggesting conservative staffing or risk assumptions. | AP28: Feb 2026
A29: BID-028 | B29: Harborlight Medical Offices – New Facility Turnover Cleaning | C29: Harborlight Medical Offices | D29: Commercial | E29: Post-Construction Cleaning | F29: Outer Region | G29: Priya Shah | H29: 46064 | I29: 46089 | J29: Closed – No-Bid | K29: No-Bid | L29: No | M29: No | N29: 114000 | O29: 114000 | P29: 146137 | Q29: 8 | R29: 12 | S29: No | T29: No | U29: Medium | V29: Geographic Distance | W29: Declined because geographic distance reduced strategic or operational fit. | AA29: Pinnacle Facility Care | AB29: 1 | AC29: 5 | AD29: 0 | AE29: 0 | AF29: 46070 | AI29: =IF(OR(X29="",Y29=""),"",X29-Y29) | AJ29: =IFERROR((X29-Y29)/Y29,"") | AK29: =IFERROR(X29/P29,"") -> 0 | AL29: =IF(AF29="","",AF29-H29) -> 6 | AM29: =IF(AG29="","",AG29-AF29) | AN29: Document decision intelligence | AO29: Resources were preserved for better-aligned pursuits. | AP29: Feb 2026
A30: BID-029 | B30: Queensboro Transit Authority – Campus Custodial Services | C30: Queensboro Transit Authority | D30: Government | E30: Custodial | F30: North Jersey | G30: Michael Ngo | H30: 46065 | I30: 46091 | J30: Closed – No-Bid | K30: No-Bid | L30: No | M30: No | N30: 469400 | O30: 938800 | P30: 184068 | Q30: 1 | R30: 24 | S30: Yes | T30: No | U30: Low | V30: Minimum Qualifications | W30: Declined because minimum qualifications reduced strategic or operational fit. | AA30: Stark Facilities Group | AB30: 2 | AC30: 2 | AD30: 0 | AE30: 0 | AF30: 46069 | AI30: =IF(OR(X30="",Y30=""),"",X30-Y30) | AJ30: =IFERROR((X30-Y30)/Y30,"") | AK30: =IFERROR(X30/P30,"") -> 0 | AL30: =IF(AF30="","",AF30-H30) -> 4 | AM30: =IF(AG30="","",AG30-AF30) | AN30: Document decision intelligence | AO30: Resources were preserved for better-aligned pursuits. | AP30: Feb 2026
A31: BID-030 | B31: Arcadia Housing Authority – Seasonal Grounds Services | C31: Arcadia Housing Authority | D31: Government | E31: Landscaping | F31: Central Jersey | G31: Avery Chen | H31: 46066 | I31: 46093 | J31: Closed – Awarded | K31: Lost | L31: Yes | M31: Yes | N31: 102100 | O31: 306300 | P31: 221999 | Q31: 8 | R31: 36 | S31: Yes | T31: No | U31: Low | W31: Pursuit aligned with the fictional bidder's service strategy; routine pursuit within demonstrated service and geographic capabilities. | X31: 306300 | Y31: 268700 | Z31: Pinnacle Facility Care | AA31: Wayne Municipal Services | AB31: 3 | AC31: 3 | AD31: 3 | AE31: 4 | AF31: 46072 | AG31: 46079 | AH31: 46140 | AI31: =IF(OR(X31="",Y31=""),"",X31-Y31) -> 37600 | AJ31: =IFERROR((X31-Y31)/Y31,"") -> 0.13993301 | AK31: =IFERROR(X31/P31,"") -> 1.3797359 | AL31: =IF(AF31="","",AF31-H31) -> 6 | AM31: =IF(AG31="","",AG31-AF31) -> 7 | AN31: Request debrief or tabulation | AO31: Result provides a usable market benchmark for future pricing. | AP31: Feb 2026
A32: BID-031 | B32: Harborlight Medical Offices – Event Security Coverage | C32: Harborlight Medical Offices | D32: Commercial | E32: Security | F32: North Jersey | G32: Jordan Ellis | H32: 46095 | I32: 46123 | J32: Closed – No-Bid | K32: No-Bid | L32: No | M32: No | N32: 170500 | O32: 170500 | Q32: 1 | R32: 12 | S32: No | T32: No | U32: High | V32: Licensing Requirement | W32: Declined because licensing requirement reduced strategic or operational fit. | AA32: Atlas Building Partners | AB32: 1 | AC32: 6 | AD32: 0 | AE32: 0 | AF32: 46102 | AI32: =IF(OR(X32="",Y32=""),"",X32-Y32) | AJ32: =IFERROR((X32-Y32)/Y32,"") | AK32: =IFERROR(X32/P32,"") | AL32: =IF(AF32="","",AF32-H32) -> 7 | AM32: =IF(AG32="","",AG32-AF32) | AN32: Document decision intelligence | AO32: Resources were preserved for better-aligned pursuits. | AP32: Mar 2026
A33: BID-032 | B33: Queensboro Transit Authority – Commercial IPM Services | C33: Queensboro Transit Authority | D33: Government | E33: Pest Control | F33: Central Jersey | G33: Priya Shah | H33: 46096 | I33: 46125 | J33: Closed – Awarded | K33: Lost | L33: Yes | M33: Yes | N33: 18000 | O33: 36000 | Q33: 8 | R33: 24 | S33: Yes | T33: No | U33: Low | W33: Pursuit aligned with the fictional bidder's service strategy; routine pursuit within demonstrated service and geographic capabilities. | X33: 36000 | Y33: 33000 | Z33: Wayne Municipal Services | AA33: Blue Lantern Services | AB33: 2 | AC33: 5 | AD33: 5 | AE33: 3 | AF33: 46103 | AG33: 46111 | AH33: 46144 | AI33: =IF(OR(X33="",Y33=""),"",X33-Y33) -> 3000 | AJ33: =IFERROR((X33-Y33)/Y33,"") -> 0.090909091 | AK33: =IFERROR(X33/P33,"") | AL33: =IF(AF33="","",AF33-H33) -> 7 | AM33: =IF(AG33="","",AG33-AF33) -> 8 | AN33: Request debrief or tabulation | AO33: Result provides a usable market benchmark for future pricing. | AP33: Mar 2026
A34: BID-033 | B34: Arcadia Housing Authority – Final Construction Cleaning | C34: Arcadia Housing Authority | D34: Government | E34: Post-Construction Cleaning | F34: Metro NY | G34: Michael Ngo | H34: 46097 | I34: 46127 | J34: Closed – No-Bid | K34: No-Bid | L34: No | M34: No | N34: 261900 | O34: 785700 | P34: 335792 | Q34: 1 | R34: 36 | S34: Yes | T34: No | U34: Low | V34: Staffing / Operations Capacity | W34: Declined because staffing / operations capacity reduced strategic or operational fit. | AA34: Sentinel Operations | AB34: 3 | AC34: 2 | AD34: 0 | AE34: 0 | AF34: 46102 | AI34: =IF(OR(X34="",Y34=""),"",X34-Y34) | AJ34: =IFERROR((X34-Y34)/Y34,"") | AK34: =IFERROR(X34/P34,"") -> 0 | AL34: =IF(AF34="","",AF34-H34) -> 5 | AM34: =IF(AG34="","",AG34-AF34) | AN34: Document decision intelligence | AO34: Resources were preserved for better-aligned pursuits. | AP34: Mar 2026
A35: BID-034 | B35: Crescent Bay University – Stone and Resilient Floor Care | C35: Crescent Bay University | D35: Education | E35: Specialty Floor Care | F35: Hudson Valley | G35: Avery Chen | H35: 46098 | I35: 46129 | J35: Closed – Awarded | K35: Won | L35: Yes | M35: Yes | N35: 127100 | O35: 127100 | P35: 373723 | Q35: 8 | R35: 12 | S35: No | T35: No | U35: Low | W35: Pursuit aligned with the fictional bidder's service strategy; routine pursuit within demonstrated service and geographic capabilities. | X35: 127100 | Y35: 127100 | Z35: Michael BidWorks | AA35: Pinnacle Facility Care | AB35: 1 | AC35: 3 | AD35: 3 | AE35: 2 | AF35: 46102 | AG35: 46107 | AH35: 46150 | AI35: =IF(OR(X35="",Y35=""),"",X35-Y35) -> 0 | AJ35: =IFERROR((X35-Y35)/Y35,"") -> 0 | AK35: =IFERROR(X35/P35,"") -> 0.34009146 | AL35: =IF(AF35="","",AF35-H35) -> 4 | AM35: =IF(AG35="","",AG35-AF35) -> 5 | AN35: Prepare transition brief | AO35: Competitive positioning and scope fit supported award. | AP35: Mar 2026
A36: BID-035 | B36: Daily Bugle Headquarters – Campus Landscape Program | C36: Daily Bugle Headquarters | D36: Commercial | E36: Landscaping | F36: Outer Region | G36: Jordan Ellis | H36: 46099 | I36: 46131 | J36: Closed – No-Bid | K36: No-Bid | L36: No | M36: No | N36: 189400 | O36: 378800 | P36: 411654 | Q36: 1 | R36: 24 | S36: No | T36: No | U36: Medium | V36: Geographic Distance | W36: Declined because geographic distance reduced strategic or operational fit. | AA36: Stark Facilities Group | AB36: 2 | AC36: 4 | AD36: 0 | AE36: 0 | AF36: 46105 | AI36: =IF(OR(X36="",Y36=""),"",X36-Y36) | AJ36: =IFERROR((X36-Y36)/Y36,"") | AK36: =IFERROR(X36/P36,"") -> 0 | AL36: =IF(AF36="","",AF36-H36) -> 6 | AM36: =IF(AG36="","",AG36-AF36) | AN36: Document decision intelligence | AO36: Resources were preserved for better-aligned pursuits. | AP36: Mar 2026
A37: BID-036 | B37: Arcadia Housing Authority – Public Offices Custodial Support | C37: Arcadia Housing Authority | D37: Government | E37: Janitorial | F37: Hudson Valley | G37: Priya Shah | H37: 46131 | I37: 46164 | J37: Closed – Awarded | K37: Lost | L37: Yes | M37: Yes | N37: 1011600 | O37: 3034800 | P37: 449585 | Q37: 8 | R37: 36 | S37: Yes | T37: Yes | U37: Low | W37: Pursuit aligned with the fictional bidder's service strategy; routine pursuit within demonstrated service and geographic capabilities. | X37: 3034800 | Y37: 2823100 | Z37: Pinnacle Facility Care | AA37: Wayne Municipal Services | AB37: 3 | AC37: 5 | AD37: 5 | AE37: 4 | AF37: 46139 | AG37: 46148 | AH37: 46187 | AI37: =IF(OR(X37="",Y37=""),"",X37-Y37) -> 211700 | AJ37: =IFERROR((X37-Y37)/Y37,"") -> 0.074988488 | AK37: =IFERROR(X37/P37,"") -> 6.7502252 | AL37: =IF(AF37="","",AF37-H37) -> 8 | AM37: =IF(AG37="","",AG37-AF37) -> 9 | AN37: Request debrief or tabulation | AO37: Result provides a usable market benchmark for future pricing. | AP37: Apr 2026
A38: BID-037 | B38: Crescent Bay University – Integrated Pest Management | C38: Crescent Bay University | D38: Education | E38: Pest Control | F38: Outer Region | G38: Michael Ngo | H38: 46114 | I38: 46148 | J38: Closed – No-Bid | K38: No-Bid | L38: No | M38: No | N38: 18000 | O38: 18000 | Q38: 1 | R38: 12 | S38: No | T38: No | U38: Medium | V38: Geographic Distance | W38: Declined because geographic distance reduced strategic or operational fit. | AA38: Atlas Building Partners | AB38: 1 | AC38: 2 | AD38: 0 | AE38: 0 | AF38: 46117 | AI38: =IF(OR(X38="",Y38=""),"",X38-Y38) | AJ38: =IFERROR((X38-Y38)/Y38,"") | AK38: =IFERROR(X38/P38,"") | AL38: =IF(AF38="","",AF38-H38) -> 3 | AM38: =IF(AG38="","",AG38-AF38) | AN38: Document decision intelligence | AO38: Resources were preserved for better-aligned pursuits. | AP38: Apr 2026
A39: BID-038 | B39: Daily Bugle Headquarters – Renovation Closeout Cleaning | C39: Daily Bugle Headquarters | D39: Commercial | E39: Post-Construction Cleaning | F39: North Jersey | G39: Avery Chen | H39: 46115 | I39: 46150 | J39: Closed – Awarded | K39: Lost | L39: Yes | M39: Yes | N39: 409800 | O39: 819600 | P39: 525447 | Q39: 8 | R39: 24 | S39: No | T39: No | U39: Low | W39: Pursuit aligned with the fictional bidder's service strategy; routine pursuit within demonstrated service and geographic capabilities. | X39: 819600 | Y39: 741700 | Z39: Wayne Municipal Services | AA39: Blue Lantern Services | AB39: 2 | AC39: 3 | AD39: 3 | AE39: 3 | AF39: 46120 | AG39: 46126 | AH39: 46175 | AI39: =IF(OR(X39="",Y39=""),"",X39-Y39) -> 77900 | AJ39: =IFERROR((X39-Y39)/Y39,"") -> 0.10502899 | AK39: =IFERROR(X39/P39,"") -> 1.5598148 | AL39: =IF(AF39="","",AF39-H39) -> 5 | AM39: =IF(AG39="","",AG39-AF39) -> 6 | AN39: Request debrief or tabulation | AO39: Result provides a usable market benchmark for future pricing. | AP39: Apr 2026
A40: BID-039 | B40: Metropolis Community College – Civic Center Custodial Program | C40: Metropolis Community College | D40: Education | E40: Custodial | F40: Central Jersey | G40: Jordan Ellis | H40: 46116 | I40: 46152 | J40: Closed – Awarded | K40: Lost | L40: Yes | M40: Yes | N40: 1436600 | O40: 4309800 | P40: 563378 | Q40: 1 | R40: 36 | S40: Yes | T40: Yes | U40: High | W40: Pursuit aligned with the fictional bidder's service strategy; requires leadership review of operating model, compliance exposure, and staffing assumptions. | X40: 4309800 | Y40: 3848000 | Z40: Atlas Building Partners | AA40: Sentinel Operations | AB40: 3 | AC40: 4 | AD40: 4 | AE40: 4 | AF40: 46123 | AG40: 46131 | AH40: 46178 | AI40: =IF(OR(X40="",Y40=""),"",X40-Y40) -> 461800 | AJ40: =IFERROR((X40-Y40)/Y40,"") -> 0.1200104 | AK40: =IFERROR(X40/P40,"") -> 7.649926 | AL40: =IF(AF40="","",AF40-H40) -> 7 | AM40: =IF(AG40="","",AG40-AF40) -> 8 | AN40: Request debrief or tabulation | AO40: Result provides a usable market benchmark for future pricing. | AP40: Apr 2026
A41: BID-040 | B41: Atlas County Services – Public Complex Operations | C41: Atlas County Services | D41: Government | E41: Facility Maintenance | F41: Metro NY | G41: Priya Shah | H41: 46117 | I41: 46154 | J41: Closed – Awarded | K41: Lost | L41: Yes | M41: Yes | N41: 3126800 | O41: 3126800 | P41: 601309 | Q41: 8 | R41: 12 | S41: No | T41: Yes | U41: High | W41: Pursuit aligned with the fictional bidder's service strategy; requires leadership review of operating model, compliance exposure, and staffing assumptions. | X41: 3126800 | Y41: 2481600 | Z41: Blue Lantern Services | AA41: Pinnacle Facility Care | AB41: 1 | AC41: 10 | AD41: 5 | AE41: 2 | AF41: 46128 | AG41: 46135 | AH41: 46181 | AI41: =IF(OR(X41="",Y41=""),"",X41-Y41) -> 645200 | AJ41: =IFERROR((X41-Y41)/Y41,"") -> 0.25999355 | AK41: =IFERROR(X41/P41,"") -> 5.1999887 | AL41: =IF(AF41="","",AF41-H41) -> 11 | AM41: =IF(AG41="","",AG41-AF41) -> 7 | AN41: Request debrief or tabulation | AO41: Price exceeded the market benchmark, suggesting conservative staffing or risk assumptions. | AP41: Apr 2026
A42: BID-041 | B42: Daily Bugle Headquarters – Unarmed Guard Services | C42: Daily Bugle Headquarters | D42: Commercial | E42: Security | F42: Central Jersey | G42: Michael Ngo | H42: 46148 | I42: 46166 | J42: Closed – No-Bid | K42: No-Bid | L42: No | M42: No | N42: 170500 | O42: 341000 | Q42: 1 | R42: 24 | S42: No | T42: No | U42: High | V42: Licensing Requirement | W42: Declined because licensing requirement reduced strategic or operational fit. | AA42: Stark Facilities Group | AB42: 2 | AC42: 7 | AD42: 0 | AE42: 0 | AF42: 46157 | AI42: =IF(OR(X42="",Y42=""),"",X42-Y42) | AJ42: =IFERROR((X42-Y42)/Y42,"") | AK42: =IFERROR(X42/P42,"") | AL42: =IF(AF42="","",AF42-H42) -> 9 | AM42: =IF(AG42="","",AG42-AF42) | AN42: Document decision intelligence | AO42: Resources were preserved for better-aligned pursuits. | AP42: May 2026
A43: BID-042 | B43: Metropolis Community College – Districtwide Pest Prevention | C43: Metropolis Community College | D43: Education | E43: Pest Control | F43: Metro NY | G43: Avery Chen | H43: 46149 | I43: 46168 | J43: Closed – Awarded | K43: Lost | L43: Yes | M43: Yes | N43: 18000 | O43: 54000 | Q43: 8 | R43: 36 | S43: Yes | T43: No | U43: Low | W43: Pursuit aligned with the fictional bidder's service strategy; routine pursuit within demonstrated service and geographic capabilities. | X43: 54000 | Y43: 49500 | Z43: Pinnacle Facility Care | AA43: Wayne Municipal Services | AB43: 3 | AC43: 3 | AD43: 3 | AE43: 4 | AF43: 46155 | AG43: 46162 | AH43: 46197 | AI43: =IF(OR(X43="",Y43=""),"",X43-Y43) -> 4500 | AJ43: =IFERROR((X43-Y43)/Y43,"") -> 0.090909091 | AK43: =IFERROR(X43/P43,"") | AL43: =IF(AF43="","",AF43-H43) -> 6 | AM43: =IF(AG43="","",AG43-AF43) -> 7 | AN43: Request debrief or tabulation | AO43: Result provides a usable market benchmark for future pricing. | AP43: May 2026
A44: BID-043 | B44: Atlas County Services – Multi-Phase Final Clean | C44: Atlas County Services | D44: Government | E44: Post-Construction Cleaning | F44: Hudson Valley | G44: Jordan Ellis | H44: 46150 | I44: 46170 | J44: Closed – Awarded | K44: Lost | L44: Yes | M44: Yes | N44: 557800 | O44: 557800 | P44: 715102 | Q44: 1 | R44: 12 | S44: No | T44: No | U44: Low | W44: Pursuit aligned with the fictional bidder's service strategy; routine pursuit within demonstrated service and geographic capabilities. | X44: 557800 | Y44: 504800 | Z44: Stark Facilities Group | AA44: Atlas Building Partners | AB44: 1 | AC44: 4 | AD44: 4 | AE44: 2 | AF44: 46155 | AG44: 46161 | AH44: 46200 | AI44: =IF(OR(X44="",Y44=""),"",X44-Y44) -> 53000 | AJ44: =IFERROR((X44-Y44)/Y44,"") -> 0.10499208 | AK44: =IFERROR(X44/P44,"") -> 0.78002858 | AL44: =IF(AF44="","",AF44-H44) -> 5 | AM44: =IF(AG44="","",AG44-AF44) -> 6 | AN44: Request debrief or tabulation | AO44: Result provides a usable market benchmark for future pricing. | AP44: May 2026
A45: BID-044 | B45: Orbit Retail Properties – Municipal Buildings Custodial Services | C45: Orbit Retail Properties | D45: Commercial | E45: Custodial | F45: Outer Region | G45: Priya Shah | H45: 46151 | I45: 46172 | J45: Closed – No-Bid | K45: No-Bid | L45: No | M45: No | N45: 1920200 | O45: 3840400 | P45: 753033 | Q45: 8 | R45: 24 | S45: No | T45: No | U45: High | V45: Geographic Distance | W45: Declined because geographic distance reduced strategic or operational fit. | AA45: Blue Lantern Services | AB45: 2 | AC45: 5 | AD45: 0 | AE45: 0 | AF45: 46158 | AI45: =IF(OR(X45="",Y45=""),"",X45-Y45) | AJ45: =IFERROR((X45-Y45)/Y45,"") | AK45: =IFERROR(X45/P45,"") -> 0 | AL45: =IF(AF45="","",AF45-H45) -> 7 | AM45: =IF(AG45="","",AG45-AF45) | AN45: Document decision intelligence | AO45: Resources were preserved for better-aligned pursuits. | AP45: May 2026
A46: BID-045 | B46: Stark Facilities Group – Annual Floor Restoration | C46: Stark Facilities Group | D46: Commercial | E46: Specialty Floor Care | F46: North Jersey | G46: Michael Ngo | H46: 46152 | I46: 46174 | J46: Closed – No-Bid | K46: No-Bid | L46: No | M46: No | N46: 268900 | O46: 806700 | P46: 790964 | Q46: 1 | R46: 36 | S46: No | T46: No | U46: Low | V46: Staffing / Operations Capacity | W46: Declined because staffing / operations capacity reduced strategic or operational fit. | AA46: Sentinel Operations | AB46: 3 | AC46: 2 | AD46: 0 | AE46: 0 | AF46: 46157 | AI46: =IF(OR(X46="",Y46=""),"",X46-Y46) | AJ46: =IFERROR((X46-Y46)/Y46,"") | AK46: =IFERROR(X46/P46,"") -> 0 | AL46: =IF(AF46="","",AF46-H46) -> 5 | AM46: =IF(AG46="","",AG46-AF46) | AN46: Document decision intelligence | AO46: Resources were preserved for better-aligned pursuits. | AP46: May 2026
A47: BID-046 | B47: Atlas County Services – Multi-Site Evening Janitorial | C47: Atlas County Services | D47: Government | E47: Janitorial | F47: Outer Region | G47: Avery Chen | H47: 46184 | I47: 46207 | J47: Closed – No-Bid | K47: No-Bid | L47: No | M47: No | N47: 1865000 | O47: 1865000 | P47: 828895 | Q47: 8 | R47: 12 | S47: No | T47: Yes | U47: High | V47: Geographic Distance | W47: Declined because geographic distance reduced strategic or operational fit. | AA47: Pinnacle Facility Care | AB47: 1 | AC47: 3 | AD47: 0 | AE47: 0 | AF47: 46188 | AI47: =IF(OR(X47="",Y47=""),"",X47-Y47) | AJ47: =IFERROR((X47-Y47)/Y47,"") | AK47: =IFERROR(X47/P47,"") -> 0 | AL47: =IF(AF47="","",AF47-H47) -> 4 | AM47: =IF(AG47="","",AG47-AF47) | AN47: Document decision intelligence | AO47: Resources were preserved for better-aligned pursuits. | AP47: Jun 2026
A48: BID-047 | B48: Orbit Retail Properties – Rodent Control Program | C48: Orbit Retail Properties | D48: Commercial | E48: Pest Control | F48: North Jersey | G48: Jordan Ellis | H48: 46185 | I48: 46209 | J48: Closed – Awarded | K48: Lost | L48: Yes | M48: Yes | N48: 18000 | O48: 36000 | Q48: 1 | R48: 24 | S48: No | T48: No | U48: Low | W48: Pursuit aligned with the fictional bidder's service strategy; routine pursuit within demonstrated service and geographic capabilities. | X48: 36000 | Y48: 33000 | Z48: Sentinel Operations | AA48: Stark Facilities Group | AB48: 2 | AC48: 4 | AD48: 4 | AE48: 3 | AF48: 46191 | AG48: 46198 | AH48: 46243 | AI48: =IF(OR(X48="",Y48=""),"",X48-Y48) -> 3000 | AJ48: =IFERROR((X48-Y48)/Y48,"") -> 0.090909091 | AK48: =IFERROR(X48/P48,"") | AL48: =IF(AF48="","",AF48-H48) -> 6 | AM48: =IF(AG48="","",AG48-AF48) -> 7 | AN48: Request debrief or tabulation | AO48: Result provides a usable market benchmark for future pricing. | AP48: Jun 2026
A49: BID-048 | B49: Stark Facilities Group – New Facility Turnover Cleaning | C49: Stark Facilities Group | D49: Commercial | E49: Post-Construction Cleaning | F49: Central Jersey | G49: Priya Shah | H49: 46186 | I49: 46211 | J49: Closed – Awarded | K49: Lost | L49: Yes | M49: Yes | N49: 18000 | O49: 54000 | P49: 14757 | Q49: 8 | R49: 36 | S49: No | T49: No | U49: Low | W49: Pursuit aligned with the fictional bidder's service strategy; routine pursuit within demonstrated service and geographic capabilities. | X49: 54000 | Y49: 48900 | Z49: Pinnacle Facility Care | AA49: Wayne Municipal Services | AB49: 3 | AC49: 5 | AD49: 5 | AE49: 4 | AF49: 46194 | AG49: 46203 | AH49: 46246 | AI49: =IF(OR(X49="",Y49=""),"",X49-Y49) -> 5100 | AJ49: =IFERROR((X49-Y49)/Y49,"") -> 0.10429448 | AK49: =IFERROR(X49/P49,"") -> 3.6592803 | AL49: =IF(AF49="","",AF49-H49) -> 8 | AM49: =IF(AG49="","",AG49-AF49) -> 9 | AN49: Request debrief or tabulation | AO49: Result provides a usable market benchmark for future pricing. | AP49: Jun 2026
A50: BID-049 | B50: Parker Research Campus – Campus Custodial Services | C50: Parker Research Campus | D50: Commercial | E50: Custodial | F50: Metro NY | G50: Michael Ngo | H50: 46187 | I50: 46213 | J50: Closed – No-Bid | K50: No-Bid | L50: No | M50: No | N50: 134400 | O50: 134400 | P50: 52688 | Q50: 1 | R50: 12 | S50: No | T50: No | U50: Low | V50: Licensing Requirement | W50: Declined because licensing requirement reduced strategic or operational fit. | AA50: Atlas Building Partners | AB50: 1 | AC50: 2 | AD50: 0 | AE50: 0 | AF50: 46190 | AI50: =IF(OR(X50="",Y50=""),"",X50-Y50) | AJ50: =IFERROR((X50-Y50)/Y50,"") | AK50: =IFERROR(X50/P50,"") -> 0 | AL50: =IF(AF50="","",AF50-H50) -> 3 | AM50: =IF(AG50="","",AG50-AF50) | AN50: Document decision intelligence | AO50: Resources were preserved for better-aligned pursuits. | AP50: Jun 2026
A51: BID-050 | B51: Beacon Preparatory Schools – Seasonal Grounds Services | C51: Beacon Preparatory Schools | D51: Education | E51: Landscaping | F51: Hudson Valley | G51: Avery Chen | H51: 46188 | I51: 46215 | J51: Closed – Awarded | K51: Lost | L51: Yes | M51: Yes | N51: 41700 | O51: 83400 | P51: 90619 | Q51: 8 | R51: 24 | S51: Yes | T51: No | U51: Low | W51: Pursuit aligned with the fictional bidder's service strategy; routine pursuit within demonstrated service and geographic capabilities. | X51: 83400 | Y51: 73200 | Z51: Wayne Municipal Services | AA51: Blue Lantern Services | AB51: 2 | AC51: 3 | AD51: 3 | AE51: 3 | AF51: 46193 | AG51: 46199 | AH51: 46252 | AI51: =IF(OR(X51="",Y51=""),"",X51-Y51) -> 10200 | AJ51: =IFERROR((X51-Y51)/Y51,"") -> 0.13934426 | AK51: =IFERROR(X51/P51,"") -> 0.92033679 | AL51: =IF(AF51="","",AF51-H51) -> 5 | AM51: =IF(AG51="","",AG51-AF51) -> 6 | AN51: Request debrief or tabulation | AO51: Result provides a usable market benchmark for future pricing. | AP51: Jun 2026
A52: BID-051 | B52: Stark Facilities Group – Event Security Coverage | C52: Stark Facilities Group | D52: Commercial | E52: Security | F52: Metro NY | G52: Jordan Ellis | H52: 46219 | I52: 46247 | J52: Closed – No-Bid | K52: No-Bid | L52: No | M52: No | N52: 170500 | O52: 511500 | Q52: 1 | R52: 36 | S52: No | T52: No | U52: High | V52: Licensing Requirement | W52: Declined because licensing requirement reduced strategic or operational fit. | AA52: Sentinel Operations | AB52: 3 | AC52: 8 | AD52: 0 | AE52: 0 | AF52: 46230 | AI52: =IF(OR(X52="",Y52=""),"",X52-Y52) | AJ52: =IFERROR((X52-Y52)/Y52,"") | AK52: =IFERROR(X52/P52,"") | AL52: =IF(AF52="","",AF52-H52) -> 11 | AM52: =IF(AG52="","",AG52-AF52) | AN52: Document decision intelligence | AO52: Resources were preserved for better-aligned pursuits. | AP52: Jul 2026
A53: BID-052 | B53: Parker Research Campus – Commercial IPM Services | C53: Parker Research Campus | D53: Commercial | E53: Pest Control | F53: Hudson Valley | G53: Priya Shah | H53: 46220 | I53: 46249 | J53: Closed – Awarded | K53: Lost | L53: Yes | M53: Yes | N53: 18000 | O53: 18000 | Q53: 8 | R53: 12 | S53: No | T53: No | U53: Low | W53: Pursuit aligned with the fictional bidder's service strategy; routine pursuit within demonstrated service and geographic capabilities. | X53: 18000 | Y53: 16500 | Z53: Blue Lantern Services | AA53: Pinnacle Facility Care | AB53: 1 | AC53: 5 | AD53: 5 | AE53: 2 | AF53: 46226 | AG53: 46233 | AH53: 46288 | AI53: =IF(OR(X53="",Y53=""),"",X53-Y53) -> 1500 | AJ53: =IFERROR((X53-Y53)/Y53,"") -> 0.090909091 | AK53: =IFERROR(X53/P53,"") | AL53: =IF(AF53="","",AF53-H53) -> 6 | AM53: =IF(AG53="","",AG53-AF53) -> 7 | AN53: Request debrief or tabulation | AO53: Result provides a usable market benchmark for future pricing. | AP53: Jul 2026
A54: BID-053 | B54: Beacon Preparatory Schools – Integrated Facility Operations | C54: Beacon Preparatory Schools | D54: Education | E54: Facility Maintenance | F54: Outer Region | G54: Michael Ngo | H54: 46221 | I54: 46251 | J54: Pricing | K54: In Progress | L54: Yes | M54: No | N54: 1062900 | O54: 2125800 | P54: 204412 | Q54: 1 | R54: 24 | S54: Yes | T54: Yes | U54: High | W54: Pursuit aligned with the fictional bidder's service strategy; requires leadership review of operating model, compliance exposure, and staffing assumptions. | AA54: Stark Facilities Group | AB54: 2 | AC54: 7 | AD54: 0 | AE54: 0 | AF54: 46230 | AI54: =IF(OR(X54="",Y54=""),"",X54-Y54) | AJ54: =IFERROR((X54-Y54)/Y54,"") | AK54: =IFERROR(X54/P54,"") -> 0 | AL54: =IF(AF54="","",AF54-H54) -> 9 | AM54: =IF(AG54="","",AG54-AF54) | AN54: Complete current-stage review | AO54: Opportunity remains active and requires continued workflow management. | AP54: Jul 2026
A55: BID-054 | B55: Wayne Municipal Services – Districtwide School Cleaning | C55: Wayne Municipal Services | D55: Government | E55: Custodial | F55: North Jersey | G55: Avery Chen | H55: 46222 | I55: 46253 | J55: Proposal Development | K55: In Progress | L55: Yes | M55: No | N55: 618000 | O55: 1854000 | P55: 242343 | Q55: 8 | R55: 36 | S55: Yes | T55: Yes | U55: Low | W55: Pursuit aligned with the fictional bidder's service strategy; routine pursuit within demonstrated service and geographic capabilities. | AA55: Wayne Municipal Services | AB55: 3 | AC55: 3 | AD55: 0 | AE55: 0 | AF55: 46228 | AI55: =IF(OR(X55="",Y55=""),"",X55-Y55) | AJ55: =IFERROR((X55-Y55)/Y55,"") | AK55: =IFERROR(X55/P55,"") -> 0 | AL55: =IF(AF55="","",AF55-H55) -> 6 | AM55: =IF(AG55="","",AG55-AF55) | AN55: Complete current-stage review | AO55: Opportunity remains active and requires continued workflow management. | AP55: Jul 2026
A56: BID-055 | B56: Emerald City Administrative Center – Campus Landscape Program | C56: Emerald City Administrative Center | D56: Government | E56: Landscaping | F56: Outer Region | G56: Jordan Ellis | H56: 46205 | I56: 46237 | J56: Submitted | K56: Submitted | L56: Yes | M56: Yes | N56: 128900 | O56: 128900 | P56: 280274 | Q56: 1 | R56: 12 | S56: No | T56: No | U56: Medium | W56: Pursuit aligned with the fictional bidder's service strategy; manageable pursuit with one or more operational dependencies requiring confirmation. | X56: 128900 | AA56: Atlas Building Partners | AB56: 1 | AC56: 4 | AD56: 4 | AE56: 2 | AF56: 46210 | AG56: 46216 | AI56: =IF(OR(X56="",Y56=""),"",X56-Y56) | AJ56: =IFERROR((X56-Y56)/Y56,"") | AK56: =IFERROR(X56/P56,"") -> 0.45990709 | AL56: =IF(AF56="","",AF56-H56) -> 5 | AM56: =IF(AG56="","",AG56-AF56) -> 6 | AN56: Confirm receipt | AO56: Opportunity remains active and requires continued workflow management. | AP56: Jul 2026
A57: BID-056 | B57: Beacon Preparatory Schools – Carpet and Floor Renewal | C57: Beacon Preparatory Schools | D57: Education | E57: Specialty Floor Care | F57: North Jersey | G57: Priya Shah | H57: 46237 | I57: 46270 | J57: Awaiting Award | K57: Awaiting Award | L57: Yes | M57: Yes | N57: 108200 | O57: 216400 | P57: 318205 | Q57: 8 | R57: 24 | S57: Yes | T57: No | U57: Low | W57: Pursuit aligned with the fictional bidder's service strategy; routine pursuit within demonstrated service and geographic capabilities. | X57: 216400 | AA57: Blue Lantern Services | AB57: 2 | AC57: 5 | AD57: 5 | AE57: 3 | AF57: 46244 | AG57: 46252 | AI57: =IF(OR(X57="",Y57=""),"",X57-Y57) | AJ57: =IFERROR((X57-Y57)/Y57,"") | AK57: =IFERROR(X57/P57,"") -> 0.68006474 | AL57: =IF(AF57="","",AF57-H57) -> 7 | AM57: =IF(AG57="","",AG57-AF57) -> 8 | AN57: Request award status | AO57: Opportunity remains active and requires continued workflow management. | AP57: Aug 2026
A58: BID-057 | B58: Wayne Municipal Services – Integrated Pest Management | C58: Wayne Municipal Services | D58: Government | E58: Pest Control | F58: Central Jersey | G58: Michael Ngo | H58: 46238 | I58: 46272 | J58: Proposal Development | K58: In Progress | L58: Yes | M58: No | N58: 18000 | O58: 54000 | Q58: 1 | R58: 36 | S58: Yes | T58: No | U58: Low | W58: Pursuit aligned with the fictional bidder's service strategy; routine pursuit within demonstrated service and geographic capabilities. | AA58: Sentinel Operations | AB58: 3 | AC58: 2 | AD58: 0 | AE58: 0 | AF58: 46243 | AI58: =IF(OR(X58="",Y58=""),"",X58-Y58) | AJ58: =IFERROR((X58-Y58)/Y58,"") | AK58: =IFERROR(X58/P58,"") | AL58: =IF(AF58="","",AF58-H58) -> 5 | AM58: =IF(AG58="","",AG58-AF58) | AN58: Complete current-stage review | AO58: Opportunity remains active and requires continued workflow management. | AP58: Aug 2026
A59: BID-058 | B59: Emerald City Administrative Center – Renovation Closeout Cleaning | C59: Emerald City Administrative Center | D59: Government | E59: Post-Construction Cleaning | F59: Metro NY | G59: Avery Chen | H59: 46239 | I59: 46274 | J59: Submitted | K59: Submitted | L59: Yes | M59: Yes | N59: 307400 | O59: 307400 | P59: 394067 | Q59: 8 | R59: 12 | S59: No | T59: No | U59: Low | W59: Pursuit aligned with the fictional bidder's service strategy; routine pursuit within demonstrated service and geographic capabilities. | X59: 307400 | AA59: Pinnacle Facility Care | AB59: 1 | AC59: 3 | AD59: 3 | AE59: 2 | AF59: 46243 | AG59: 46248 | AI59: =IF(OR(X59="",Y59=""),"",X59-Y59) | AJ59: =IFERROR((X59-Y59)/Y59,"") | AK59: =IFERROR(X59/P59,"") -> 0.78007039 | AL59: =IF(AF59="","",AF59-H59) -> 4 | AM59: =IF(AG59="","",AG59-AF59) -> 5 | AN59: Confirm receipt | AO59: Opportunity remains active and requires continued workflow management. | AP59: Aug 2026
A60: BID-059 | B60: Keystone Civic Complex – Civic Center Custodial Program | C60: Keystone Civic Complex | D60: Government | E60: Custodial | F60: Hudson Valley | G60: Jordan Ellis | H60: 46240 | I60: 46276 | J60: Awaiting Award | K60: Awaiting Award | L60: Yes | M60: Yes | N60: 1101600 | O60: 2203200 | P60: 431998 | Q60: 1 | R60: 24 | S60: Yes | T60: Yes | U60: Low | W60: Pursuit aligned with the fictional bidder's service strategy; routine pursuit within demonstrated service and geographic capabilities. | X60: 2203200 | AA60: Stark Facilities Group | AB60: 2 | AC60: 4 | AD60: 4 | AE60: 3 | AF60: 46246 | AG60: 46253 | AI60: =IF(OR(X60="",Y60=""),"",X60-Y60) | AJ60: =IFERROR((X60-Y60)/Y60,"") | AK60: =IFERROR(X60/P60,"") -> 5.1000236 | AL60: =IF(AF60="","",AF60-H60) -> 6 | AM60: =IF(AG60="","",AG60-AF60) -> 7 | AN60: Request award status | AO60: Opportunity remains active and requires continued workflow management. | AP60: Aug 2026
A61: BID-060 | B61: Gotham Public Schools – Municipal Grounds Care | C61: Gotham Public Schools | D61: Education | E61: Landscaping | F61: Outer Region | G61: Priya Shah | H61: 46241 | I61: 46278 | J61: Proposal Development | K61: In Progress | L61: Yes | M61: No | N61: 216200 | O61: 648600 | P61: 469929 | Q61: 8 | R61: 36 | S61: Yes | T61: No | U61: Medium | W61: Pursuit aligned with the fictional bidder's service strategy; manageable pursuit with one or more operational dependencies requiring confirmation. | AA61: Wayne Municipal Services | AB61: 3 | AC61: 5 | AD61: 0 | AE61: 0 | AF61: 46249 | AI61: =IF(OR(X61="",Y61=""),"",X61-Y61) | AJ61: =IFERROR((X61-Y61)/Y61,"") | AK61: =IFERROR(X61/P61,"") -> 0 | AL61: =IF(AF61="","",AF61-H61) -> 8 | AM61: =IF(AG61="","",AG61-AF61) | AN61: Complete current-stage review | AO61: Opportunity remains active and requires continued workflow management. | AP61: Aug 2026

Sheet 2. Executive Dashboard
A1: EXECUTIVE BID INTELLIGENCE | B1: EXECUTIVE BID INTELLIGENCE | C1: EXECUTIVE BID INTELLIGENCE | D1: EXECUTIVE BID INTELLIGENCE | E1: EXECUTIVE BID INTELLIGENCE | F1: EXECUTIVE BID INTELLIGENCE | G1: EXECUTIVE BID INTELLIGENCE | H1: EXECUTIVE BID INTELLIGENCE | I1: EXECUTIVE BID INTELLIGENCE | J1: EXECUTIVE BID INTELLIGENCE | K1: EXECUTIVE BID INTELLIGENCE | L1: EXECUTIVE BID INTELLIGENCE | M1: EXECUTIVE BID INTELLIGENCE | N1: EXECUTIVE BID INTELLIGENCE
A2: Portfolio-wide performance, pipeline value, and pursuit outcomes | Fictional demonstration | B2: Portfolio-wide performance, pipeline value, and pursuit outcomes | Fictional demonstration | C2: Portfolio-wide performance, pipeline value, and pursuit outcomes | Fictional demonstration | D2: Portfolio-wide performance, pipeline value, and pursuit outcomes | Fictional demonstration | E2: Portfolio-wide performance, pipeline value, and pursuit outcomes | Fictional demonstration | F2: Portfolio-wide performance, pipeline value, and pursuit outcomes | Fictional demonstration | G2: Portfolio-wide performance, pipeline value, and pursuit outcomes | Fictional demonstration | H2: Portfolio-wide performance, pipeline value, and pursuit outcomes | Fictional demonstration | I2: Portfolio-wide performance, pipeline value, and pursuit outcomes | Fictional demonstration | J2: Portfolio-wide performance, pipeline value, and pursuit outcomes | Fictional demonstration | K2: Portfolio-wide performance, pipeline value, and pursuit outcomes | Fictional demonstration | L2: Portfolio-wide performance, pipeline value, and pursuit outcomes | Fictional demonstration | M2: Portfolio-wide performance, pipeline value, and pursuit outcomes | Fictional demonstration | N2: Portfolio-wide performance, pipeline value, and pursuit outcomes | Fictional demonstration
A3: Reporting Period | B3: Reporting Period | C3: All Periods | D3: All Periods | E3: ← Click for Drop Down
A5: OPPORTUNITIES REVIEWED | B5: OPPORTUNITIES REVIEWED | D5: SUBMITTED | E5: SUBMITTED | G5: WINS | H5: WINS | J5: NO-BIDS | K5: NO-BIDS | M5: DECIDED WIN RATE | N5: DECIDED WIN RATE
A6: =IF($C$3="All Periods",COUNTA('1. Opportunity Register'!$A$2:$A$61),COUNTIF('1. Opportunity Register'!$AP$2:$AP$61,$C$3)) -> 60 | D6: =IF($C$3="All Periods",COUNTIF('1. Opportunity Register'!$M$2:$M$61,"Yes"),COUNTIFS('1. Opportunity Register'!$M$2:$M$61,"Yes",'1. Opportunity Register'!$AP$2:$AP$61,$C$3)) -> 33 | G6: =IF($C$3="All Periods",COUNTIF('1. Opportunity Register'!$K$2:$K$61,"Won"),COUNTIFS('1. Opportunity Register'!$K$2:$K$61,"Won",'1. Opportunity Register'!$AP$2:$AP$61,$C$3)) -> 3 | J6: =IF($C$3="All Periods",COUNTIF('1. Opportunity Register'!$K$2:$K$61,"No-Bid"),COUNTIFS('1. Opportunity Register'!$K$2:$K$61,"No-Bid",'1. Opportunity Register'!$AP$2:$AP$61,$C$3)) -> 23 | M6: =IFERROR(G6/(G6+IF($C$3="All Periods",COUNTIF('1. Opportunity Register'!$K$2:$K$61,"Lost"),COUNTIFS('1. Opportunity Register'!$K$2:$K$61,"Lost",'1. Opportunity Register'!$AP$2:$AP$61,$C$3))),0) -> 0.10344828
A9: SUBMITTED VALUE | B9: SUBMITTED VALUE | C9: SUBMITTED VALUE | E9: ACTIVE PIPELINE VALUE | F9: ACTIVE PIPELINE VALUE | G9: ACTIVE PIPELINE VALUE | I9: AVERAGE CONTRACT VALUE | J9: AVERAGE CONTRACT VALUE | K9: AVERAGE CONTRACT VALUE | M9: AWAITING AWARD | N9: AWAITING AWARD
A10: =IF($C$3="All Periods",SUM('1. Opportunity Register'!$X$2:$X$61),SUMIFS('1. Opportunity Register'!$X$2:$X$61,'1. Opportunity Register'!$AP$2:$AP$61,$C$3)) -> 36813700 | E10: =IF($C$3="All Periods",SUMIFS('1. Opportunity Register'!$O$2:$O$61,'1. Opportunity Register'!$K$2:$K$61,"In Progress")+SUMIFS('1. Opportunity Register'!$O$2:$O$61,'1. Opportunity Register'!$K$2:$K$61,"Submitted")+SUMIFS('1. Opportunity Register'!$O$2:$O$61,'1. Opportunity Register'!$K$2:$K$61,"Awaiting Award"),SUMIFS('1. Opportunity Register'!$O$2:$O$61,'1. Opportunity Register'!$AP$2:$AP$61,$C$3,'1. Opportunity Register'!$K$2:$K$61,"In Progress")+SUMIFS('1. Opportunity Register'!$O$2:$O$61,'1. Opportunity Register'!$AP$2:$AP$61,$C$3,'1. Opportunity Register'!$K$2:$K$61,"Submitted")+SUMIFS('1. Opportunity Register'!$O$2:$O$61,'1. Opportunity Register'!$AP$2:$AP$61,$C$3,'1. Opportunity Register'!$K$2:$K$61,"Awaiting Award")) -> 7538300 | I10: =IFERROR(IF($C$3="All Periods",AVERAGEIF('1. Opportunity Register'!$O$2:$O$61,">0"),SUMIFS('1. Opportunity Register'!$O$2:$O$61,'1. Opportunity Register'!$AP$2:$AP$61,$C$3)/COUNTIF('1. Opportunity Register'!$AP$2:$AP$61,$C$3)),0) -> 958906.67 | M10: =IF($C$3="All Periods",COUNTIF('1. Opportunity Register'!$K$2:$K$61,"Awaiting Award"),COUNTIFS('1. Opportunity Register'!$K$2:$K$61,"Awaiting Award",'1. Opportunity Register'!$AP$2:$AP$61,$C$3)) -> 2
A30: Month | B30: Reviewed | C30: Submitted | D30: Wins | E30: No-Bids | G30: Outcome | H30: Count
A31: Sep 2025 | B31: =IF(OR($C$3="All Periods",$C$3=A31),COUNTIF('1. Opportunity Register'!$AP$2:$AP$61,A31),"") -> 5 | C31: =IF(OR($C$3="All Periods",$C$3=A31),COUNTIFS('1. Opportunity Register'!$M$2:$M$61,"Yes",'1. Opportunity Register'!$AP$2:$AP$61,A31),"") -> 2 | D31: =IF(OR($C$3="All Periods",$C$3=A31),COUNTIFS('1. Opportunity Register'!$K$2:$K$61,"Won",'1. Opportunity Register'!$AP$2:$AP$61,A31),"") -> 0 | E31: =IF(OR($C$3="All Periods",$C$3=A31),COUNTIFS('1. Opportunity Register'!$K$2:$K$61,"No-Bid",'1. Opportunity Register'!$AP$2:$AP$61,A31),"") -> 3 | G31: Won | H31: =IF($C$3="All Periods",COUNTIF('1. Opportunity Register'!$K$2:$K$61,G31),COUNTIFS('1. Opportunity Register'!$K$2:$K$61,G31,'1. Opportunity Register'!$AP$2:$AP$61,$C$3)) -> 3
A32: Oct 2025 | B32: =IF(OR($C$3="All Periods",$C$3=A32),COUNTIF('1. Opportunity Register'!$AP$2:$AP$61,A32),"") -> 5 | C32: =IF(OR($C$3="All Periods",$C$3=A32),COUNTIFS('1. Opportunity Register'!$M$2:$M$61,"Yes",'1. Opportunity Register'!$AP$2:$AP$61,A32),"") -> 3 | D32: =IF(OR($C$3="All Periods",$C$3=A32),COUNTIFS('1. Opportunity Register'!$K$2:$K$61,"Won",'1. Opportunity Register'!$AP$2:$AP$61,A32),"") -> 0 | E32: =IF(OR($C$3="All Periods",$C$3=A32),COUNTIFS('1. Opportunity Register'!$K$2:$K$61,"No-Bid",'1. Opportunity Register'!$AP$2:$AP$61,A32),"") -> 2 | G32: Lost | H32: =IF($C$3="All Periods",COUNTIF('1. Opportunity Register'!$K$2:$K$61,G32),COUNTIFS('1. Opportunity Register'!$K$2:$K$61,G32,'1. Opportunity Register'!$AP$2:$AP$61,$C$3)) -> 26
A33: Nov 2025 | B33: =IF(OR($C$3="All Periods",$C$3=A33),COUNTIF('1. Opportunity Register'!$AP$2:$AP$61,A33),"") -> 5 | C33: =IF(OR($C$3="All Periods",$C$3=A33),COUNTIFS('1. Opportunity Register'!$M$2:$M$61,"Yes",'1. Opportunity Register'!$AP$2:$AP$61,A33),"") -> 3 | D33: =IF(OR($C$3="All Periods",$C$3=A33),COUNTIFS('1. Opportunity Register'!$K$2:$K$61,"Won",'1. Opportunity Register'!$AP$2:$AP$61,A33),"") -> 0 | E33: =IF(OR($C$3="All Periods",$C$3=A33),COUNTIFS('1. Opportunity Register'!$K$2:$K$61,"No-Bid",'1. Opportunity Register'!$AP$2:$AP$61,A33),"") -> 2 | G33: No-Bid | H33: =IF($C$3="All Periods",COUNTIF('1. Opportunity Register'!$K$2:$K$61,G33),COUNTIFS('1. Opportunity Register'!$K$2:$K$61,G33,'1. Opportunity Register'!$AP$2:$AP$61,$C$3)) -> 23
A34: Dec 2025 | B34: =IF(OR($C$3="All Periods",$C$3=A34),COUNTIF('1. Opportunity Register'!$AP$2:$AP$61,A34),"") -> 5 | C34: =IF(OR($C$3="All Periods",$C$3=A34),COUNTIFS('1. Opportunity Register'!$M$2:$M$61,"Yes",'1. Opportunity Register'!$AP$2:$AP$61,A34),"") -> 3 | D34: =IF(OR($C$3="All Periods",$C$3=A34),COUNTIFS('1. Opportunity Register'!$K$2:$K$61,"Won",'1. Opportunity Register'!$AP$2:$AP$61,A34),"") -> 0 | E34: =IF(OR($C$3="All Periods",$C$3=A34),COUNTIFS('1. Opportunity Register'!$K$2:$K$61,"No-Bid",'1. Opportunity Register'!$AP$2:$AP$61,A34),"") -> 2 | G34: Awaiting Award | H34: =IF($C$3="All Periods",COUNTIF('1. Opportunity Register'!$K$2:$K$61,G34),COUNTIFS('1. Opportunity Register'!$K$2:$K$61,G34,'1. Opportunity Register'!$AP$2:$AP$61,$C$3)) -> 2
A35: Jan 2026 | B35: =IF(OR($C$3="All Periods",$C$3=A35),COUNTIF('1. Opportunity Register'!$AP$2:$AP$61,A35),"") -> 5 | C35: =IF(OR($C$3="All Periods",$C$3=A35),COUNTIFS('1. Opportunity Register'!$M$2:$M$61,"Yes",'1. Opportunity Register'!$AP$2:$AP$61,A35),"") -> 3 | D35: =IF(OR($C$3="All Periods",$C$3=A35),COUNTIFS('1. Opportunity Register'!$K$2:$K$61,"Won",'1. Opportunity Register'!$AP$2:$AP$61,A35),"") -> 1 | E35: =IF(OR($C$3="All Periods",$C$3=A35),COUNTIFS('1. Opportunity Register'!$K$2:$K$61,"No-Bid",'1. Opportunity Register'!$AP$2:$AP$61,A35),"") -> 2 | G35: Submitted | H35: =IF($C$3="All Periods",COUNTIF('1. Opportunity Register'!$K$2:$K$61,G35),COUNTIFS('1. Opportunity Register'!$K$2:$K$61,G35,'1. Opportunity Register'!$AP$2:$AP$61,$C$3)) -> 2
A36: Feb 2026 | B36: =IF(OR($C$3="All Periods",$C$3=A36),COUNTIF('1. Opportunity Register'!$AP$2:$AP$61,A36),"") -> 5 | C36: =IF(OR($C$3="All Periods",$C$3=A36),COUNTIFS('1. Opportunity Register'!$M$2:$M$61,"Yes",'1. Opportunity Register'!$AP$2:$AP$61,A36),"") -> 3 | D36: =IF(OR($C$3="All Periods",$C$3=A36),COUNTIFS('1. Opportunity Register'!$K$2:$K$61,"Won",'1. Opportunity Register'!$AP$2:$AP$61,A36),"") -> 1 | E36: =IF(OR($C$3="All Periods",$C$3=A36),COUNTIFS('1. Opportunity Register'!$K$2:$K$61,"No-Bid",'1. Opportunity Register'!$AP$2:$AP$61,A36),"") -> 2 | G36: In Progress | H36: =IF($C$3="All Periods",COUNTIF('1. Opportunity Register'!$K$2:$K$61,G36),COUNTIFS('1. Opportunity Register'!$K$2:$K$61,G36,'1. Opportunity Register'!$AP$2:$AP$61,$C$3)) -> 4
A37: Mar 2026 | B37: =IF(OR($C$3="All Periods",$C$3=A37),COUNTIF('1. Opportunity Register'!$AP$2:$AP$61,A37),"") -> 5 | C37: =IF(OR($C$3="All Periods",$C$3=A37),COUNTIFS('1. Opportunity Register'!$M$2:$M$61,"Yes",'1. Opportunity Register'!$AP$2:$AP$61,A37),"") -> 2 | D37: =IF(OR($C$3="All Periods",$C$3=A37),COUNTIFS('1. Opportunity Register'!$K$2:$K$61,"Won",'1. Opportunity Register'!$AP$2:$AP$61,A37),"") -> 1 | E37: =IF(OR($C$3="All Periods",$C$3=A37),COUNTIFS('1. Opportunity Register'!$K$2:$K$61,"No-Bid",'1. Opportunity Register'!$AP$2:$AP$61,A37),"") -> 3
A38: Apr 2026 | B38: =IF(OR($C$3="All Periods",$C$3=A38),COUNTIF('1. Opportunity Register'!$AP$2:$AP$61,A38),"") -> 5 | C38: =IF(OR($C$3="All Periods",$C$3=A38),COUNTIFS('1. Opportunity Register'!$M$2:$M$61,"Yes",'1. Opportunity Register'!$AP$2:$AP$61,A38),"") -> 4 | D38: =IF(OR($C$3="All Periods",$C$3=A38),COUNTIFS('1. Opportunity Register'!$K$2:$K$61,"Won",'1. Opportunity Register'!$AP$2:$AP$61,A38),"") -> 0 | E38: =IF(OR($C$3="All Periods",$C$3=A38),COUNTIFS('1. Opportunity Register'!$K$2:$K$61,"No-Bid",'1. Opportunity Register'!$AP$2:$AP$61,A38),"") -> 1
A39: May 2026 | B39: =IF(OR($C$3="All Periods",$C$3=A39),COUNTIF('1. Opportunity Register'!$AP$2:$AP$61,A39),"") -> 5 | C39: =IF(OR($C$3="All Periods",$C$3=A39),COUNTIFS('1. Opportunity Register'!$M$2:$M$61,"Yes",'1. Opportunity Register'!$AP$2:$AP$61,A39),"") -> 2 | D39: =IF(OR($C$3="All Periods",$C$3=A39),COUNTIFS('1. Opportunity Register'!$K$2:$K$61,"Won",'1. Opportunity Register'!$AP$2:$AP$61,A39),"") -> 0 | E39: =IF(OR($C$3="All Periods",$C$3=A39),COUNTIFS('1. Opportunity Register'!$K$2:$K$61,"No-Bid",'1. Opportunity Register'!$AP$2:$AP$61,A39),"") -> 3
A40: Jun 2026 | B40: =IF(OR($C$3="All Periods",$C$3=A40),COUNTIF('1. Opportunity Register'!$AP$2:$AP$61,A40),"") -> 5 | C40: =IF(OR($C$3="All Periods",$C$3=A40),COUNTIFS('1. Opportunity Register'!$M$2:$M$61,"Yes",'1. Opportunity Register'!$AP$2:$AP$61,A40),"") -> 3 | D40: =IF(OR($C$3="All Periods",$C$3=A40),COUNTIFS('1. Opportunity Register'!$K$2:$K$61,"Won",'1. Opportunity Register'!$AP$2:$AP$61,A40),"") -> 0 | E40: =IF(OR($C$3="All Periods",$C$3=A40),COUNTIFS('1. Opportunity Register'!$K$2:$K$61,"No-Bid",'1. Opportunity Register'!$AP$2:$AP$61,A40),"") -> 2
A41: Jul 2026 | B41: =IF(OR($C$3="All Periods",$C$3=A41),COUNTIF('1. Opportunity Register'!$AP$2:$AP$61,A41),"") -> 5 | C41: =IF(OR($C$3="All Periods",$C$3=A41),COUNTIFS('1. Opportunity Register'!$M$2:$M$61,"Yes",'1. Opportunity Register'!$AP$2:$AP$61,A41),"") -> 2 | D41: =IF(OR($C$3="All Periods",$C$3=A41),COUNTIFS('1. Opportunity Register'!$K$2:$K$61,"Won",'1. Opportunity Register'!$AP$2:$AP$61,A41),"") -> 0 | E41: =IF(OR($C$3="All Periods",$C$3=A41),COUNTIFS('1. Opportunity Register'!$K$2:$K$61,"No-Bid",'1. Opportunity Register'!$AP$2:$AP$61,A41),"") -> 1
A42: Aug 2026 | B42: =IF(OR($C$3="All Periods",$C$3=A42),COUNTIF('1. Opportunity Register'!$AP$2:$AP$61,A42),"") -> 5 | C42: =IF(OR($C$3="All Periods",$C$3=A42),COUNTIFS('1. Opportunity Register'!$M$2:$M$61,"Yes",'1. Opportunity Register'!$AP$2:$AP$61,A42),"") -> 3 | D42: =IF(OR($C$3="All Periods",$C$3=A42),COUNTIFS('1. Opportunity Register'!$K$2:$K$61,"Won",'1. Opportunity Register'!$AP$2:$AP$61,A42),"") -> 0 | E42: =IF(OR($C$3="All Periods",$C$3=A42),COUNTIFS('1. Opportunity Register'!$K$2:$K$61,"No-Bid",'1. Opportunity Register'!$AP$2:$AP$61,A42),"") -> 0

Sheet 3. Active Pipeline
A1: ACTIVE BID PIPELINE | B1: ACTIVE BID PIPELINE | C1: ACTIVE BID PIPELINE | D1: ACTIVE BID PIPELINE | E1: ACTIVE BID PIPELINE | F1: ACTIVE BID PIPELINE | G1: ACTIVE BID PIPELINE | H1: ACTIVE BID PIPELINE | I1: ACTIVE BID PIPELINE | J1: ACTIVE BID PIPELINE | K1: ACTIVE BID PIPELINE | L1: ACTIVE BID PIPELINE | M1: ACTIVE BID PIPELINE | N1: ACTIVE BID PIPELINE
A3: Opportunity ID | B3: Opportunity | C3: Client | D3: Service | E3: Market | F3: Due Date | G3: Stage | H3: Est. Total Value | I3: SF | J3: Sites | K3: Prevailing Wage | L3: Owner | M3: Risk | N3: Next Action
A4: BID-053 | B4: Beacon Preparatory Schools – Integrated Facility Operations | C4: Beacon Preparatory Schools | D4: Facility Maintenance | E4: Outer Region | F4: 46251 | G4: Pricing | H4: 2125800 | I4: 204412 | J4: 1 | K4: Yes | L4: Michael Ngo | M4: High | N4: Complete current-stage review
A5: BID-054 | B5: Wayne Municipal Services – Districtwide School Cleaning | C5: Wayne Municipal Services | D5: Custodial | E5: North Jersey | F5: 46253 | G5: Proposal Development | H5: 1854000 | I5: 242343 | J5: 8 | K5: Yes | L5: Avery Chen | M5: Low | N5: Complete current-stage review
A6: BID-055 | B6: Emerald City Administrative Center – Campus Landscape Program | C6: Emerald City Administrative Center | D6: Landscaping | E6: Outer Region | F6: 46237 | G6: Submitted | H6: 128900 | I6: 280274 | J6: 1 | K6: No | L6: Jordan Ellis | M6: Medium | N6: Confirm receipt
A7: BID-056 | B7: Beacon Preparatory Schools – Carpet and Floor Renewal | C7: Beacon Preparatory Schools | D7: Specialty Floor Care | E7: North Jersey | F7: 46270 | G7: Awaiting Award | H7: 216400 | I7: 318205 | J7: 8 | K7: Yes | L7: Priya Shah | M7: Low | N7: Request award status
A8: BID-057 | B8: Wayne Municipal Services – Integrated Pest Management | C8: Wayne Municipal Services | D8: Pest Control | E8: Central Jersey | F8: 46272 | G8: Proposal Development | H8: 54000 | J8: 1 | K8: Yes | L8: Michael Ngo | M8: Low | N8: Complete current-stage review
A9: BID-058 | B9: Emerald City Administrative Center – Renovation Closeout Cleaning | C9: Emerald City Administrative Center | D9: Post-Construction Cleaning | E9: Metro NY | F9: 46274 | G9: Submitted | H9: 307400 | I9: 394067 | J9: 8 | K9: No | L9: Avery Chen | M9: Low | N9: Confirm receipt
A10: BID-059 | B10: Keystone Civic Complex – Civic Center Custodial Program | C10: Keystone Civic Complex | D10: Custodial | E10: Hudson Valley | F10: 46276 | G10: Awaiting Award | H10: 2203200 | I10: 431998 | J10: 1 | K10: Yes | L10: Jordan Ellis | M10: Low | N10: Request award status
A11: BID-060 | B11: Gotham Public Schools – Municipal Grounds Care | C11: Gotham Public Schools | D11: Landscaping | E11: Outer Region | F11: 46278 | G11: Proposal Development | H11: 648600 | I11: 469929 | J11: 8 | K11: Yes | L11: Priya Shah | M11: Medium | N11: Complete current-stage review

Sheet 4. Bid-No-Bid Intelligence
A1: BID / NO-BID INTELLIGENCE | B1: BID / NO-BID INTELLIGENCE | C1: BID / NO-BID INTELLIGENCE | D1: BID / NO-BID INTELLIGENCE | E1: BID / NO-BID INTELLIGENCE | F1: BID / NO-BID INTELLIGENCE | G1: BID / NO-BID INTELLIGENCE | H1: BID / NO-BID INTELLIGENCE | I1: BID / NO-BID INTELLIGENCE | J1: BID / NO-BID INTELLIGENCE | K1: BID / NO-BID INTELLIGENCE | L1: BID / NO-BID INTELLIGENCE | M1: BID / NO-BID INTELLIGENCE | N1: BID / NO-BID INTELLIGENCE
A2: Reporting Period | B2: Reporting Period | C2: All Periods | D2: All Periods | E2: ← Click for Drop Down
A3: DECLINED OPPORTUNITIES | B3: DECLINED OPPORTUNITIES | C3: DECLINED OPPORTUNITIES | E3: NO-BID RATE | F3: NO-BID RATE | G3: NO-BID RATE | I3: VALUE DECLINED | J3: VALUE DECLINED | K3: VALUE DECLINED | M3: EST. HOURS AVOIDED | N3: EST. HOURS AVOIDED
A4: =IF($C$2="All Periods",COUNTIF('1. Opportunity Register'!$K$2:$K$61,"No-Bid"),COUNTIFS('1. Opportunity Register'!$K$2:$K$61,"No-Bid",'1. Opportunity Register'!$AP$2:$AP$61,$C$2)) -> 23 | E4: =IFERROR(A4/IF($C$2="All Periods",COUNTA('1. Opportunity Register'!$A$2:$A$61),COUNTIF('1. Opportunity Register'!$AP$2:$AP$61,$C$2)),0) -> 0.38333333 | I4: =IF($C$2="All Periods",SUMIFS('1. Opportunity Register'!$O$2:$O$61,'1. Opportunity Register'!$K$2:$K$61,"No-Bid"),SUMIFS('1. Opportunity Register'!$O$2:$O$61,'1. Opportunity Register'!$K$2:$K$61,"No-Bid",'1. Opportunity Register'!$AP$2:$AP$61,$C$2)) -> 16038300 | M4: =A4*18 -> 414
A28: No-Bid Reason | B28: Count | H28: Market | I28: Count
A29: Geographic Distance | B29: =IF($C$2="All Periods",COUNTIFS('1. Opportunity Register'!$K$2:$K$61,"No-Bid",'1. Opportunity Register'!$V$2:$V$61,A29),COUNTIFS('1. Opportunity Register'!$K$2:$K$61,"No-Bid",'1. Opportunity Register'!$V$2:$V$61,A29,'1. Opportunity Register'!$AP$2:$AP$61,$C$2)) -> 13 | H29: Metro NY | I29: =IF($C$2="All Periods",COUNTIFS('1. Opportunity Register'!$K$2:$K$61,"No-Bid",'1. Opportunity Register'!$F$2:$F$61,H29),COUNTIFS('1. Opportunity Register'!$K$2:$K$61,"No-Bid",'1. Opportunity Register'!$F$2:$F$61,H29,'1. Opportunity Register'!$AP$2:$AP$61,$C$2)) -> 4
A30: Licensing Requirement | B30: =IF($C$2="All Periods",COUNTIFS('1. Opportunity Register'!$K$2:$K$61,"No-Bid",'1. Opportunity Register'!$V$2:$V$61,A30),COUNTIFS('1. Opportunity Register'!$K$2:$K$61,"No-Bid",'1. Opportunity Register'!$V$2:$V$61,A30,'1. Opportunity Register'!$AP$2:$AP$61,$C$2)) -> 4 | H30: North Jersey | I30: =IF($C$2="All Periods",COUNTIFS('1. Opportunity Register'!$K$2:$K$61,"No-Bid",'1. Opportunity Register'!$F$2:$F$61,H30),COUNTIFS('1. Opportunity Register'!$K$2:$K$61,"No-Bid",'1. Opportunity Register'!$F$2:$F$61,H30,'1. Opportunity Register'!$AP$2:$AP$61,$C$2)) -> 4
A31: Scope Misalignment | B31: =IF($C$2="All Periods",COUNTIFS('1. Opportunity Register'!$K$2:$K$61,"No-Bid",'1. Opportunity Register'!$V$2:$V$61,A31),COUNTIFS('1. Opportunity Register'!$K$2:$K$61,"No-Bid",'1. Opportunity Register'!$V$2:$V$61,A31,'1. Opportunity Register'!$AP$2:$AP$61,$C$2)) -> 1 | H31: Hudson Valley | I31: =IF($C$2="All Periods",COUNTIFS('1. Opportunity Register'!$K$2:$K$61,"No-Bid",'1. Opportunity Register'!$F$2:$F$61,H31),COUNTIFS('1. Opportunity Register'!$K$2:$K$61,"No-Bid",'1. Opportunity Register'!$F$2:$F$61,H31,'1. Opportunity Register'!$AP$2:$AP$61,$C$2)) -> 2
A32: Staffing / Operations Capacity | B32: =IF($C$2="All Periods",COUNTIFS('1. Opportunity Register'!$K$2:$K$61,"No-Bid",'1. Opportunity Register'!$V$2:$V$61,A32),COUNTIFS('1. Opportunity Register'!$K$2:$K$61,"No-Bid",'1. Opportunity Register'!$V$2:$V$61,A32,'1. Opportunity Register'!$AP$2:$AP$61,$C$2)) -> 2 | H32: Central Jersey | I32: =IF($C$2="All Periods",COUNTIFS('1. Opportunity Register'!$K$2:$K$61,"No-Bid",'1. Opportunity Register'!$F$2:$F$61,H32),COUNTIFS('1. Opportunity Register'!$K$2:$K$61,"No-Bid",'1. Opportunity Register'!$F$2:$F$61,H32,'1. Opportunity Register'!$AP$2:$AP$61,$C$2)) -> 2
A33: Insufficient Time | B33: =IF($C$2="All Periods",COUNTIFS('1. Opportunity Register'!$K$2:$K$61,"No-Bid",'1. Opportunity Register'!$V$2:$V$61,A33),COUNTIFS('1. Opportunity Register'!$K$2:$K$61,"No-Bid",'1. Opportunity Register'!$V$2:$V$61,A33,'1. Opportunity Register'!$AP$2:$AP$61,$C$2)) -> 1 | H33: Outer Region | I33: =IF($C$2="All Periods",COUNTIFS('1. Opportunity Register'!$K$2:$K$61,"No-Bid",'1. Opportunity Register'!$F$2:$F$61,H33),COUNTIFS('1. Opportunity Register'!$K$2:$K$61,"No-Bid",'1. Opportunity Register'!$F$2:$F$61,H33,'1. Opportunity Register'!$AP$2:$AP$61,$C$2)) -> 11
A34: Minimum Qualifications | B34: =IF($C$2="All Periods",COUNTIFS('1. Opportunity Register'!$K$2:$K$61,"No-Bid",'1. Opportunity Register'!$V$2:$V$61,A34),COUNTIFS('1. Opportunity Register'!$K$2:$K$61,"No-Bid",'1. Opportunity Register'!$V$2:$V$61,A34,'1. Opportunity Register'!$AP$2:$AP$61,$C$2)) -> 2
A35: Pricing / Margin Concern | B35: =IF($C$2="All Periods",COUNTIFS('1. Opportunity Register'!$K$2:$K$61,"No-Bid",'1. Opportunity Register'!$V$2:$V$61,A35),COUNTIFS('1. Opportunity Register'!$K$2:$K$61,"No-Bid",'1. Opportunity Register'!$V$2:$V$61,A35,'1. Opportunity Register'!$AP$2:$AP$61,$C$2)) -> 0
A38: Opportunity | B38: Service | C38: Market | D38: Reason | E38: Est. Value | F38: Risk | G38: Decision Note | H38: Owner
A39: Daily Bugle Headquarters – Integrated Facility Operations | B39: Facility Maintenance | C39: Outer Region | D39: Geographic Distance | E39: 62400 | F39: High | G39: Declined because geographic distance reduced strategic or operational fit. | H39: Michael Ngo
A40: Atlas County Services – Multi-Phase Final Clean | B40: Post-Construction Cleaning | C40: Outer Region | D40: Geographic Distance | E40: 205500 | F40: Medium | G40: Declined because geographic distance reduced strategic or operational fit. | H40: Jordan Ellis
A41: Stark Facilities Group – Grounds and Landscape Maintenance | B41: Landscaping | C41: Central Jersey | D41: Insufficient Time | E41: 150600 | F41: Low | G41: Declined because insufficient time reduced strategic or operational fit. | H41: Michael Ngo
A42: Parker Research Campus – Campus Custodial Services | B42: Custodial | C42: Hudson Valley | D42: Scope Misalignment | E42: 2413200 | F42: Low | G42: Declined because scope misalignment reduced strategic or operational fit. | H42: Michael Ngo
A43: Beacon Preparatory Schools – Seasonal Grounds Services | B43: Landscaping | C43: Outer Region | D43: Geographic Distance | E43: 162600 | F43: Medium | G43: Declined because geographic distance reduced strategic or operational fit. | H43: Avery Chen
A44: Parker Research Campus – Carpet and Floor Renewal | B44: Specialty Floor Care | C44: Outer Region | D44: Geographic Distance | E44: 437700 | F44: Medium | G44: Declined because geographic distance reduced strategic or operational fit. | H44: Priya Shah
A45: Beacon Preparatory Schools – Final Construction Cleaning | B45: Post-Construction Cleaning | C45: North Jersey | D45: Geographic Distance | E45: 364400 | F45: Low | G45: Declined because geographic distance reduced strategic or operational fit. | H45: Michael Ngo
A46: Wayne Municipal Services – Integrated Pest Management | B46: Pest Control | C46: Metro NY | D46: Minimum Qualifications | E46: 36000 | F46: Low | G46: Declined because minimum qualifications reduced strategic or operational fit. | H46: Michael Ngo
A47: Keystone Civic Complex – Civic Center Custodial Program | B47: Custodial | C47: Outer Region | D47: Geographic Distance | E47: 1771600 | F47: High | G47: Declined because geographic distance reduced strategic or operational fit. | H47: Jordan Ellis
A48: Emerald City Administrative Center – Unarmed Guard Services | B48: Security | C48: Outer Region | D48: Geographic Distance | E48: 511500 | F48: High | G48: Declined because geographic distance reduced strategic or operational fit. | H48: Michael Ngo
A49: Harborlight Medical Offices – Grounds and Landscape Maintenance | B49: Landscaping | C49: Hudson Valley | D49: Geographic Distance | E49: 18000 | F49: Low | G49: Declined because geographic distance reduced strategic or operational fit. | H49: Michael Ngo
A50: Harborlight Medical Offices – New Facility Turnover Cleaning | B50: Post-Construction Cleaning | C50: Outer Region | D50: Geographic Distance | E50: 114000 | F50: Medium | G50: Declined because geographic distance reduced strategic or operational fit. | H50: Priya Shah
... A61: Stark Facilities Group – Event Security Coverage | B61: Security | C61: Metro NY | D61: Licensing Requirement | E61: 511500 | F61: High | G61: Declined because licensing requirement reduced strategic or operational fit. | H61: Jordan Ellis

Sheet 5. Post-Bid Analysis
A1: POST-BID COMPETITIVE INTELLIGENCE | B1: POST-BID COMPETITIVE INTELLIGENCE | C1: POST-BID COMPETITIVE INTELLIGENCE | D1: POST-BID COMPETITIVE INTELLIGENCE | E1: POST-BID COMPETITIVE INTELLIGENCE | F1: POST-BID COMPETITIVE INTELLIGENCE | G1: POST-BID COMPETITIVE INTELLIGENCE | H1: POST-BID COMPETITIVE INTELLIGENCE | I1: POST-BID COMPETITIVE INTELLIGENCE | J1: POST-BID COMPETITIVE INTELLIGENCE | K1: POST-BID COMPETITIVE INTELLIGENCE | L1: POST-BID COMPETITIVE INTELLIGENCE | M1: POST-BID COMPETITIVE INTELLIGENCE | N1: POST-BID COMPETITIVE INTELLIGENCE
A3: DECISIONS ANALYZED | B3: DECISIONS ANALYZED | C3: DECISIONS ANALYZED | E3: AVERAGE KNOWN VARIANCE | F3: AVERAGE KNOWN VARIANCE | G3: AVERAGE KNOWN VARIANCE | I3: CLOSE / BENCHMARK | J3: CLOSE / BENCHMARK | K3: CLOSE / BENCHMARK | M3: MAJOR PRICING GAPS | N3: MAJOR PRICING GAPS
A4: =COUNTIF('1. Opportunity Register'!$K$2:$K$61,"Won")+COUNTIF('1. Opportunity Register'!$K$2:$K$61,"Lost") -> 29 | E4: =IFERROR(SUM('1. Opportunity Register'!$AI$2:$AI$61)/SUM('1. Opportunity Register'!$Y$2:$Y$61),0) -> 0.14545835 | I4: =COUNTIFS('1. Opportunity Register'!$AJ$2:$AJ$61,">0",'1. Opportunity Register'!$AJ$2:$AJ$61,"<=0.12") -> 16 | M4: =COUNTIF('1. Opportunity Register'!$AJ$2:$AJ$61,">0.20") -> 3
A28: Service | B28: Avg Variance | H28: Category | I28: Count
A29: Janitorial | B29: =IFERROR(AVERAGEIF('1. Opportunity Register'!$E$2:$E$61,A29,'1. Opportunity Register'!$AJ$2:$AJ$61),0) -> 0.056255514 | H29: Win / Not a pricing loss | I29: =COUNTIF('1. Opportunity Register'!$K$2:$K$61,"Won") -> 3
A30: Custodial | B30: =IFERROR(AVERAGEIF('1. Opportunity Register'!$E$2:$E$61,A30,'1. Opportunity Register'!$AJ$2:$AJ$61),0) -> 0.12003961 | H30: Close loss (≤12%) | I30: =COUNTIFS('1. Opportunity Register'!$AJ$2:$AJ$61,">0",'1. Opportunity Register'!$AJ$2:$AJ$61,"<=0.12") -> 16
A31: Facility Maintenance | B31: =IFERROR(AVERAGEIF('1. Opportunity Register'!$E$2:$E$61,A31,'1. Opportunity Register'!$AJ$2:$AJ$61),0) -> 0.25999071 | H31: Moderate gap (12–20%) | I31: =COUNTIFS('1. Opportunity Register'!$AJ$2:$AJ$61,">0.12",'1. Opportunity Register'!$AJ$2:$AJ$61,"<=0.20") -> 7
A32: Pest Control | B32: =IFERROR(AVERAGEIF('1. Opportunity Register'!$E$2:$E$61,A32,'1. Opportunity Register'!$AJ$2:$AJ$61),0) -> 0.090909091 | H32: Major gap (>20%) | I32: =COUNTIF('1. Opportunity Register'!$AJ$2:$AJ$61,">0.20") -> 3
A33: Landscaping | B33: =IFERROR(AVERAGEIF('1. Opportunity Register'!$E$2:$E$61,A33,'1. Opportunity Register'!$AJ$2:$AJ$61),0) -> 0.13981916
A34: Security | B34: =IFERROR(AVERAGEIF('1. Opportunity Register'!$E$2:$E$61,A34,'1. Opportunity Register'!$AJ$2:$AJ$61),0) -> 0.1799308
A35: Post-Construction Cleaning | B35: =IFERROR(AVERAGEIF('1. Opportunity Register'!$E$2:$E$61,A35,'1. Opportunity Register'!$AJ$2:$AJ$61),0) -> 0.10483145
A36: Specialty Floor Care | B36: =IFERROR(AVERAGEIF('1. Opportunity Register'!$E$2:$E$61,A36,'1. Opportunity Register'!$AJ$2:$AJ$61),0) -> 0
A40: Opportunity | B40: Service | C40: Market | D40: Outcome | E40: Submitted Price | F40: Winning Price | G40: Variance $ | H40: Variance % | I40: Price / SF | J40: Winner | K40: Incumbent | L40: Key Finding
A41: Metropolis Community College – Districtwide Pest Prevention | B41: Pest Control | C41: Hudson Valley | D41: Lost | E41: 36000 | F41: 33000 | G41: =E41-F41 -> 3000 | H41: =IFERROR(G41/F41,0) -> 0.090909091 | I41: =IFERROR(E41/'1. Opportunity Register'!P3,"") | J41: Wayne Municipal Services | K41: Blue Lantern Services | L41: Result provides a usable market benchmark for future pricing.
A42: Orbit Retail Properties – Municipal Buildings Custodial Services | B42: Custodial | C42: North Jersey | D42: Lost | E42: 320800 | F42: 286400 | G42: =E42-F42 -> 34400 | H42: =IFERROR(G42/F42,0) -> 0.12011173 | I42: =IFERROR(E42/'1. Opportunity Register'!P5,"") -> 2.5502214 | J42: Blue Lantern Services | K42: Pinnacle Facility Care | L42: Result provides a usable market benchmark for future pricing.
A43: Atlas County Services – Multi-Site Evening Janitorial | B43: Janitorial | C43: North Jersey | D43: Lost | E43: 1361100 | F43: 1266100 | G43: =E43-F43 -> 95000 | H43: =IFERROR(G43/F43,0) -> 0.075033568 | I43: =IFERROR(E43/'1. Opportunity Register'!P7,"") -> 6.7496467 | J43: Pinnacle Facility Care | K43: Wayne Municipal Services | L43: Result provides a usable market benchmark for future pricing.
A44: Orbit Retail Properties – Rodent Control Program | B44: Pest Control | C44: Central Jersey | D44: Lost | E44: 18000 | F44: 16500 | G44: =E44-F44 -> 1500 | H44: =IFERROR(G44/F44,0) -> 0.090909091 | I44: =IFERROR(E44/'1. Opportunity Register'!P8,"") | J44: Stark Facilities Group | K44: Atlas Building Partners | L44: Result provides a usable market benchmark for future pricing.
A45: Stark Facilities Group – New Facility Turnover Cleaning | B45: Post-Construction Cleaning | C45: Metro NY | D45: Lost | E45: 433000 | F45: 391900 | G45: =E45-F45 -> 41100 | H45: =IFERROR(G45/F45,0) -> 0.10487369 | I45: =IFERROR(E45/'1. Opportunity Register'!P9,"") -> 1.5602648 | J45: Wayne Municipal Services | K45: Blue Lantern Services | L45: Result provides a usable market benchmark for future pricing.
A46: Stark Facilities Group – Event Security Coverage | B46: Security | C46: Hudson Valley | D46: Lost | E46: 341000 | F46: 289000 | G46: =E46-F46 -> 52000 | H46: =IFERROR(G46/F46,0) -> 0.1799308 | I46: =IFERROR(E46/'1. Opportunity Register'!P12,"") | J46: Sentinel Operations | K46: Stark Facilities Group | L46: Result provides a usable market benchmark for future pricing.
A47: Wayne Municipal Services – Technical Building Maintenance | B47: Facility Maintenance | C47: Central Jersey | D47: Lost | E47: 5253000 | F47: 4169000 | G47: =E47-F47 -> 1084000 | H47: =IFERROR(G47/F47,0) -> 0.26001439 | I47: =IFERROR(E47/'1. Opportunity Register'!P15,"") -> 10.399859 | J47: Wayne Municipal Services | K47: Blue Lantern Services | L47: Price exceeded the market benchmark, suggesting conservative staffing or risk assumptions.
A48: Emerald City Administrative Center – Campus Landscape Program | B48: Landscaping | C48: Metro NY | D48: Lost | E48: 749400 | F48: 657400 | G48: =E48-F48 -> 92000 | H48: =IFERROR(G48/F48,0) -> 0.13994524 | I48: =IFERROR(E48/'1. Opportunity Register'!P16,"") -> 1.3800241 | J48: Atlas Building Partners | K48: Sentinel Operations | L48: Result provides a usable market benchmark for future pricing.
A49: Beacon Preparatory Schools – Public Offices Custodial Support | B49: Janitorial | C49: Central Jersey | D49: Lost | E49: 1307200 | F49: 1216000 | G49: =E49-F49 -> 91200 | H49: =IFERROR(G49/F49,0) -> 0.075 | I49: =IFERROR(E49/'1. Opportunity Register'!P17,"") -> 2.2500495 | J49: Blue Lantern Services | K49: Pinnacle Facility Care | L49: Result provides a usable market benchmark for future pricing.
A50: Emerald City Administrative Center – Renovation Closeout Cleaning | B50: Post-Construction Cleaning | C50: Hudson Valley | D50: Lost | E50: 1536900 | F50: 1390900 | G50: =E50-F50 -> 146000 | H50: =IFERROR(G50/F50,0) -> 0.10496801 | I50: =IFERROR(E50/'1. Opportunity Register'!P19,"") -> 2.3398855 | J50: Pinnacle Facility Care | K50: Wayne Municipal Services | L50: Result provides a usable market benchmark for future pricing.
A51: Gotham Public Schools – Municipal Grounds Care | B51: Landscaping | C51: North Jersey | D51: Lost | E51: 674000 | F51: 591200 | G51: =E51-F51 -> 82800 | H51: =IFERROR(G51/F51,0) -> 0.14005413 | I51: =IFERROR(E51/'1. Opportunity Register'!P21,"") -> 0.91989917 | J51: Wayne Municipal Services | K51: Blue Lantern Services | L51: Result provides a usable market benchmark for future pricing.
A52: Keystone Civic Complex – Districtwide Pest Prevention | B52: Pest Control | C52: North Jersey | D52: Lost | E52: 18000 | F52: 16500 | G52: =E52-F52 -> 1500 | H52: =IFERROR(G52/F52,0) -> 0.090909091 | I52: =IFERROR(E52/'1. Opportunity Register'!P23,"") | J52: Blue Lantern Services | K52: Pinnacle Facility Care | L52: Result provides a usable market benchmark for future pricing.
A53: Gotham Public Schools – Districtwide Floor Services | B53: Specialty Floor Care | C53: Central Jersey | D53: Won | E53: 575600 | F53: 575600 | G53: =E53-F53 -> 0 | H53: =IFERROR(G53/F53,0) -> 0 | I53: =IFERROR(E53/'1. Opportunity Register'!P24,"") -> 0.67999083 | J53: Michael BidWorks | K53: Stark Facilities Group | L53: Competitive positioning and scope fit supported award.
A54: Northstar Charter Network – Municipal Buildings Custodial Services | B54: Custodial | C54: Metro NY | D54: Lost | E54: 6765900 | F54: 6041000 | G54: =E54-F54 -> 724900 | H54: =IFERROR(G54/F54,0) -> 0.11999669 | I54: =IFERROR(E54/'1. Opportunity Register'!P25,"") -> 7.6501589 | J54: Pinnacle Facility Care | K54: Wayne Municipal Services | L54: Result provides a usable market benchmark for future pricing.
A55: Gotham Public Schools – Multi-Site Evening Janitorial | B55: Janitorial | C55: Metro NY | D55: Won | E55: 316200 | F55: 316200 | G55: =E55-F55 -> 0 | H55: =IFERROR(G55/F55,0) -> 0 | I55: =IFERROR(E55/'1. Opportunity Register'!P27,"") -> 4.4994664 | J55: Michael BidWorks | K55: Blue Lantern Services | L55: Competitive positioning and scope fit supported award.
A56: Northstar Charter Network – Multi-Site Facility Services | B56: Facility Maintenance | C56: Hudson Valley | D56: Lost | E56: 1688100 | F56: 1339800 | G56: =E56-F56 -> 348300 | H56: =IFERROR(G56/F56,0) -> 0.25996417 | I56: =IFERROR(E56/'1. Opportunity Register'!P28,"") -> 15.600798 | J56: Atlas Building Partners | K56: Sentinel Operations | L56: Price exceeded the market benchmark, suggesting conservative staffing or risk assumptions.
A57: Arcadia Housing Authority – Seasonal Grounds Services | B57: Landscaping | C57: Central Jersey | D57: Lost | E57: 306300 | F57: 268700 | G57: =E57-F57 -> 37600 | H57: =IFERROR(G57/F57,0) -> 0.13993301 | I57: =IFERROR(E57/'1. Opportunity Register'!P31,"") -> 1.3797359 | J57: Pinnacle Facility Care | K57: Wayne Municipal Services | L57: Result provides a usable market benchmark for future pricing.
A58: Queensboro Transit Authority – Commercial IPM Services | B58: Pest Control | C58: Central Jersey | D58: Lost | E58: 36000 | F58: 33000 | G58: =E58-F58 -> 3000 | H58: =IFERROR(G58/F58,0) -> 0.090909091 | I58: =IFERROR(E58/'1. Opportunity Register'!P33,"") | J58: Wayne Municipal Services | K58: Blue Lantern Services | L58: Result provides a usable market benchmark for future pricing.
A59: Crescent Bay University – Stone and Resilient Floor Care | B59: Specialty Floor Care | C59: Hudson Valley | D59: Won | E59: 127100 | F59: 127100 | G59: =E59-F59 -> 0 | H59: =IFERROR(G59/F59,0) -> 0 | I59: =IFERROR(E59/'1. Opportunity Register'!P35,"") -> 0.34009146 | J59: Michael BidWorks | K59: Pinnacle Facility Care | L59: Competitive positioning and scope fit supported award.
A60: Arcadia Housing Authority – Public Offices Custodial Support | B60: Janitorial | C60: Hudson Valley | D60: Lost | E60: 3034800 | F60: 2823100 | G60: =E60-F60 -> 211700 | H60: =IFERROR(G60/F60,0) -> 0.074988488 | I60: =IFERROR(E60/'1. Opportunity Register'!P37,"") -> 6.7502252 | J60: Pinnacle Facility Care | K60: Wayne Municipal Services | L60: Result provides a usable market benchmark for future pricing.
A61: Daily Bugle Headquarters – Renovation Closeout Cleaning | B61: Post-Construction Cleaning | C61: North Jersey | D61: Lost | E61: 819600 | F61: 741700 | G61: =E61-F61 -> 77900 | H61: =IFERROR(G61/F61,0) -> 0.10502899 | I61: =IFERROR(E61/'1. Opportunity Register'!P39,"") -> 1.5598148 | J61: Wayne Municipal Services | K61: Blue Lantern Services | L61: Result provides a usable market benchmark for future pricing.
A62: Metropolis Community College – Civic Center Custodial Program | B62: Custodial | C62: Central Jersey | D62: Lost | E62: 4309800 | F62: 3848000 | G62: =E62-F62 -> 461800 | H62: =IFERROR(G62/F62,0) -> 0.1200104 | I62: =IFERROR(E62/'1. Opportunity Register'!P40,"") -> 7.649926 | J62: Atlas Building Partners | K62: Sentinel Operations | L62: Result provides a usable market benchmark for future pricing.
A63: Atlas County Services – Public Complex Operations | B63: Facility Maintenance | C63: Metro NY | D63: Lost | E63: 3126800 | F63: 2481600 | G63: =E63-F63 -> 645200 | H63: =IFERROR(G63/F63,0) -> 0.25999355 | I63: =IFERROR(E63/'1. Opportunity Register'!P41,"") -> 5.1999887 | J63: Blue Lantern Services | K63: Pinnacle Facility Care | L63: Price exceeded the market benchmark, suggesting conservative staffing or risk assumptions.
A64: Metropolis Community College – Districtwide Pest Prevention | B64: Pest Control | C64: Metro NY | D64: Lost | E64: 54000 | F64: 49500 | G64: =E64-F64 -> 4500 | H64: =IFERROR(G64/F64,0) -> 0.090909091 | I64: =IFERROR(E64/'1. Opportunity Register'!P3,"") | J64: Pinnacle Facility Care | K64: Wayne Municipal Services | L64: Result provides a usable market benchmark for future pricing.
A65: Atlas County Services – Multi-Phase Final Clean | B65: Post-Construction Cleaning | C65: Hudson Valley | D65: Lost | E65: 557800 | F65: 504800 | G65: =E65-F65 -> 53000 | H65: =IFERROR(G65/F65,0) -> 0.10499208 | I65: =IFERROR(E65/'1. Opportunity Register'!P4,"") -> 6.3485921 | J65: Stark Facilities Group | K65: Atlas Building Partners | L65: Result provides a usable market benchmark for future pricing.
A66: Orbit Retail Properties – Rodent Control Program | B66: Pest Control | C66: North Jersey | D66: Lost | E66: 36000 | F66: 33000 | G66: =E66-F66 -> 3000 | H66: =IFERROR(G66/F66,0) -> 0.090909091 | I66: =IFERROR(E66/'1. Opportunity Register'!P8,"") | J66: Sentinel Operations | K66: Stark Facilities Group | L66: Result provides a usable market benchmark for future pricing.
A67: Stark Facilities Group – New Facility Turnover Cleaning | B67: Post-Construction Cleaning | C67: Central Jersey | D67: Lost | E67: 54000 | F67: 48900 | G67: =E67-F67 -> 5100 | H67: =IFERROR(G67/F67,0) -> 0.10429448 | I67: =IFERROR(E67/'1. Opportunity Register'!P9,"") -> 0.19458267 | J67: Pinnacle Facility Care | K67: Wayne Municipal Services | L67: Result provides a usable market benchmark for future pricing.
A68: Beacon Preparatory Schools – Seasonal Grounds Services | B68: Landscaping | C68: Hudson Valley | D68: Lost | E68: 83400 | F68: 73200 | G68: =E68-F68 -> 10200 | H68: =IFERROR(G68/F68,0) -> 0.13934426 | I68: =IFERROR(E68/'1. Opportunity Register'!P11,"") -> 0.23600723 | J68: Wayne Municipal Services | K68: Blue Lantern Services | L68: Result provides a usable market benchmark for future pricing.
A69: Parker Research Campus – Commercial IPM Services | B69: Pest Control | C69: Hudson Valley | D69: Lost | E69: 18000 | F69: 16500 | G69: =E69-F69 -> 1500 | H69: =IFERROR(G69/F69,0) -> 0.090909091 | I69: =IFERROR(E69/'1. Opportunity Register'!P53,"") | J69: Blue Lantern Services | K69: Pinnacle Facility Care | L69: Result provides a usable market benchmark for future pricing.

Sheet 6. Workflow Intelligence
A1: WORKFLOW / PROCESS INTELLIGENCE | B1: WORKFLOW / PROCESS INTELLIGENCE | C1: WORKFLOW / PROCESS INTELLIGENCE | D1: WORKFLOW / PROCESS INTELLIGENCE | E1: WORKFLOW / PROCESS INTELLIGENCE | F1: WORKFLOW / PROCESS INTELLIGENCE | G1: WORKFLOW / PROCESS INTELLIGENCE | H1: WORKFLOW / PROCESS INTELLIGENCE | I1: WORKFLOW / PROCESS INTELLIGENCE | J1: WORKFLOW / PROCESS INTELLIGENCE | K1: WORKFLOW / PROCESS INTELLIGENCE | L1: WORKFLOW / PROCESS INTELLIGENCE | M1: WORKFLOW / PROCESS INTELLIGENCE | N1: WORKFLOW / PROCESS INTELLIGENCE
A3: AVG. REVIEW TIME | B3: AVG. REVIEW TIME | C3: AVG. REVIEW TIME | E3: AVG. OPS REVIEW | F3: AVG. OPS REVIEW | G3: AVG. OPS REVIEW | I3: AVG. PROPOSAL TURNAROUND | J3: AVG. PROPOSAL TURNAROUND | K3: AVG. PROPOSAL TURNAROUND | M3: ACTIVE OPPORTUNITIES | N3: ACTIVE OPPORTUNITIES
A4: =AVERAGE('1. Opportunity Register'!$AB$2:$AB$61) -> 2 | E4: =AVERAGE('1. Opportunity Register'!$AC$2:$AC$61) -> 4.25 | I4: =AVERAGEIF('1. Opportunity Register'!$AM$2:$AM$61,">0") -> 6.969697 | M4: =COUNTIF('1. Opportunity Register'!$K$2:$K$61,"In Progress")+COUNTIF('1. Opportunity Register'!$K$2:$K$61,"Submitted")+COUNTIF('1. Opportunity Register'!$K$2:$K$61,"Awaiting Award") -> 8
A26: Stage | B26: Avg. Duration | H26: Owner | I26: Open Actions
A27: Initial Review | B27: =AVERAGEIF('8. Workflow Events'!$B$2:$B$241,A27,'8. Workflow Events'!$C$2:$C$241) -> 2 | H27: Michael Ngo | I27: =COUNTIFS('1. Opportunity Register'!$G$2:$G$61,H27,'1. Opportunity Register'!$K$2:$K$61,"In Progress")+COUNTIFS('1. Opportunity Register'!$G$2:$G$61,H27,'1. Opportunity Register'!$K$2:$K$61,"Submitted")+COUNTIFS('1. Opportunity Register'!$G$2:$G$61,H27,'1. Opportunity Register'!$K$2:$K$61,"Awaiting Award") -> 2
A28: Operational Review | B28: =AVERAGEIF('8. Workflow Events'!$B$2:$B$241,A28,'8. Workflow Events'!$C$2:$C$241) -> 4.25 | H28: Avery Chen | I28: =COUNTIFS('1. Opportunity Register'!$G$2:$G$61,H28,'1. Opportunity Register'!$K$2:$K$61,"In Progress")+COUNTIFS('1. Opportunity Register'!$G$2:$G$61,H28,'1. Opportunity Register'!$K$2:$K$61,"Submitted")+COUNTIFS('1. Opportunity Register'!$G$2:$G$61,H28,'1. Opportunity Register'!$K$2:$K$61,"Awaiting Award") -> 2
A29: Pricing | B29: =AVERAGEIF('8. Workflow Events'!$B$2:$B$241,A29,'8. Workflow Events'!$C$2:$C$241) -> 2.1833333 | H29: Jordan Ellis | I29: =COUNTIFS('1. Opportunity Register'!$G$2:$G$61,H29,'1. Opportunity Register'!$K$2:$K$61,"In Progress")+COUNTIFS('1. Opportunity Register'!$G$2:$G$61,H29,'1. Opportunity Register'!$K$2:$K$61,"Submitted")+COUNTIFS('1. Opportunity Register'!$G$2:$G$61,H29,'1. Opportunity Register'!$K$2:$K$61,"Awaiting Award") -> 2
A30: Proposal Development | B30: =AVERAGEIF('8. Workflow Events'!$B$2:$B$241,A30,'8. Workflow Events'!$C$2:$C$241) -> 1.65 | H30: Priya Shah | I30: =COUNTIFS('1. Opportunity Register'!$G$2:$G$61,H30,'1. Opportunity Register'!$K$2:$K$61,"In Progress")+COUNTIFS('1. Opportunity Register'!$G$2:$G$61,H30,'1. Opportunity Register'!$K$2:$K$61,"Submitted")+COUNTIFS('1. Opportunity Register'!$G$2:$G$61,H30,'1. Opportunity Register'!$K$2:$K$61,"Awaiting Award") -> 2
A36: Opportunity | B36: Stage | C36: Owner | D36: Due Date | E36: Risk | F36: Days to Decision | G36: Proposal Turnaround | H36: Next Action
A37: Beacon Preparatory Schools – Integrated Facility Operations | B37: Pricing | C37: Michael Ngo | D37: 46251 | E37: High | F37: 9 | G37: 0 | H37: Complete current-stage review
A38: Wayne Municipal Services – Districtwide School Cleaning | B38: Proposal Development | C38: Avery Chen | D38: 46253 | E38: Low | F38: 6 | G38: 0 | H38: Complete current-stage review
A39: Emerald City Administrative Center – Campus Landscape Program | B39: Submitted | C39: Jordan Ellis | D39: 46237 | E39: Medium | F39: 5 | G39: 6 | H39: Confirm receipt
A40: Beacon Preparatory Schools – Carpet and Floor Renewal | B40: Awaiting Award | C40: Priya Shah | D40: 46270 | E40: Low | F40: 7 | G40: 8 | H40: Request award status
A41: Wayne Municipal Services – Integrated Pest Management | B41: Proposal Development | C41: Michael Ngo | D41: 46272 | E41: Low | F41: 5 | G41: 0 | H41: Complete current-stage review
A42: Emerald City Administrative Center – Renovation Closeout Cleaning | B42: Submitted | C42: Avery Chen | D42: 46274 | E42: Low | F42: 4 | G42: 5 | H42: Confirm receipt
A43: Keystone Civic Complex – Civic Center Custodial Program | B43: Awaiting Award | C43: Jordan Ellis | D43: 46276 | E43: Low | F43: 6 | G43: 7 | H43: Request award status
A44: Gotham Public Schools – Municipal Grounds Care | B44: Proposal Development | C44: Priya Shah | D44: 46278 | E44: Medium | F44: 8 | G44: 0 | H44: Complete current-stage review

Sheet 7. Opportunity Detail
A1: OPPORTUNITY DETAIL VIEW | B1: OPPORTUNITY DETAIL VIEW | C1: OPPORTUNITY DETAIL VIEW | D1: OPPORTUNITY DETAIL VIEW | E1: OPPORTUNITY DETAIL VIEW | F1: OPPORTUNITY DETAIL VIEW | G1: OPPORTUNITY DETAIL VIEW | H1: OPPORTUNITY DETAIL VIEW | I1: OPPORTUNITY DETAIL VIEW | J1: OPPORTUNITY DETAIL VIEW
A3: Select Opportunity ID | B3: Select Opportunity ID | C3: BID-011 | D3: BID-001
A6: Opportunity | B6: Opportunity | C6: =IFERROR(INDEX('1. Opportunity Register'!$B$2:$B$61,MATCH($C$3,'1. Opportunity Register'!$A$2:$A$61,0)),"") -> Stark Facilities Group – Event Security Coverage
A7: Client | B7: Client | C7: =IFERROR(INDEX('1. Opportunity Register'!$C$2:$C$61,MATCH($C$3,'1. Opportunity Register'!$A$2:$A$61,0)),"") -> Stark Facilities Group
A8: Client Type | B8: Client Type | C8: =IFERROR(INDEX('1. Opportunity Register'!$D$2:$D$61,MATCH($C$3,'1. Opportunity Register'!$A$2:$A$61,0)),"") -> Commercial
A9: Service | B9: Service | C9: =IFERROR(INDEX('1. Opportunity Register'!$E$2:$E$61,MATCH($C$3,'1. Opportunity Register'!$A$2:$A$61,0)),"") -> Security
A10: Market | B10: Market | C10: =IFERROR(INDEX('1. Opportunity Register'!$F$2:$F$61,MATCH($C$3,'1. Opportunity Register'!$A$2:$A$61,0)),"") -> Hudson Valley
A11: Owner | B11: Owner | C11: =IFERROR(INDEX('1. Opportunity Register'!$G$2:$G$61,MATCH($C$3,'1. Opportunity Register'!$A$2:$A$61,0)),"") -> Jordan Ellis
A12: Due Date | B12: Due Date | C12: =IFERROR(INDEX('1. Opportunity Register'!$I$2:$I$61,MATCH($C$3,'1. Opportunity Register'!$A$2:$A$61,0)),"") -> 46001
A13: Current Stage | B13: Current Stage | C13: =IFERROR(INDEX('1. Opportunity Register'!$J$2:$J$61,MATCH($C$3,'1. Opportunity Register'!$A$2:$A$61,0)),"") -> Closed – Awarded
A14: Outcome | B14: Outcome | C14: =IFERROR(INDEX('1. Opportunity Register'!$K$2:$K$61,MATCH($C$3,'1. Opportunity Register'!$A$2:$A$61,0)),"") -> Lost
A15: Estimated Total Value | B15: Estimated Total Value | C15: =IFERROR(INDEX('1. Opportunity Register'!$O$2:$O$61,MATCH($C$3,'1. Opportunity Register'!$A$2:$A$61,0)),"") -> 341000
A16: Square Feet | B16: Square Feet | C16: =IFERROR(INDEX('1. Opportunity Register'!$P$2:$P$61,MATCH($C$3,'1. Opportunity Register'!$A$2:$A$61,0)),"") -> 0
A17: Site Count | B17: Site Count | C17: =IFERROR(INDEX('1. Opportunity Register'!$Q$2:$Q$61,MATCH($C$3,'1. Opportunity Register'!$A$2:$A$61,0)),"") -> 1
A18: Term | B18: Term | C18: =IFERROR(INDEX('1. Opportunity Register'!$R$2:$R$61,MATCH($C$3,'1. Opportunity Register'!$A$2:$A$61,0)),"") -> 24
A19: Prevailing Wage | B19: Prevailing Wage | C19: =IFERROR(INDEX('1. Opportunity Register'!$S$2:$S$61,MATCH($C$3,'1. Opportunity Register'!$A$2:$A$61,0)),"") -> No
A20: Bond Required | B20: Bond Required | C20: =IFERROR(INDEX('1. Opportunity Register'!$T$2:$T$61,MATCH($C$3,'1. Opportunity Register'!$A$2:$A$61,0)),"") -> No
A21: Risk Level | B21: Risk Level | C21: =IFERROR(INDEX('1. Opportunity Register'!$U$2:$U$61,MATCH($C$3,'1. Opportunity Register'!$A$2:$A$61,0)),"") -> High
A22: No-Bid Reason | B22: No-Bid Reason | C22: =IFERROR(INDEX('1. Opportunity Register'!$V$2:$V$61,MATCH($C$3,'1. Opportunity Register'!$A$2:$A$61,0)),"") -> 0
A23: Decision Notes | B23: Decision Notes | C23: =IFERROR(INDEX('1. Opportunity Register'!$W$2:$W$61,MATCH($C$3,'1. Opportunity Register'!$A$2:$A$61,0)),"") -> Pursuit aligned with the fictional bidder's service strategy; requires leadership review of operating model, compliance exposure, and staffing assumptions.
A24: Submitted Price | B24: Submitted Price | C24: =IFERROR(INDEX('1. Opportunity Register'!$X$2:$X$61,MATCH($C$3,'1. Opportunity Register'!$A$2:$A$61,0)),"") -> 341000
A25: Winning Price | B25: Winning Price | C25: =IFERROR(INDEX('1. Opportunity Register'!$Y$2:$Y$61,MATCH($C$3,'1. Opportunity Register'!$A$2:$A$61,0)),"") -> 289000
A26: Winner | B26: Winner | C26: =IFERROR(INDEX('1. Opportunity Register'!$Z$2:$Z$61,MATCH($C$3,'1. Opportunity Register'!$A$2:$A$61,0)),"") -> Sentinel Operations
A27: Incumbent | B27: Incumbent | C27: =IFERROR(INDEX('1. Opportunity Register'!$AA$2:$AA$61,MATCH($C$3,'1. Opportunity Register'!$A$2:$A$61,0)),"") -> Stark Facilities Group
A28: Next Action | B28: Next Action | C28: =IFERROR(INDEX('1. Opportunity Register'!$AN$2:$AN$61,MATCH($C$3,'1. Opportunity Register'!$A$2:$A$61,0)),"") -> Request debrief or tabulation
A29: Key Finding | B29: Key Finding | C29: =IFERROR(INDEX('1. Opportunity Register'!$AO$2:$AO$61,MATCH($C$3,'1. Opportunity Register'!$A$2:$A$61,0)),"") -> Result provides a usable market benchmark for future pricing.

Sheet 8. Workflow Events
A1: Column1 | B1: Stage | C1: Duration (Days) | D1: Owner
A2: BID-001 | B2: Initial Review | C2: 1 | D2: Michael Ngo
A3: BID-001 | B3: Operational Review | C3: 7 | D3: Michael Ngo
A4: BID-001 | B4: Pricing | C4: 0 | D4: Michael Ngo
A5: BID-001 | B5: Proposal Development | C5: 0 | D5: Michael Ngo
A6: BID-002 | B6: Initial Review | C6: 2 | D6: Avery Chen
A7: BID-002 | B7: Operational Review | C7: 3 | D7: Avery Chen
A8: BID-002 | B8: Pricing | C8: 3 | D8: Avery Chen
A9: BID-002 | B9: Proposal Development | C9: 3 | D9: Avery Chen
A10: BID-003 | B10: Initial Review | C10: 3 | D10: Jordan Ellis
A11: BID-003 | B11: Operational Review | C11: 4 | D11: Jordan Ellis
A12: BID-003 | B12: Pricing | C12: 0 | D12: Jordan Ellis
A13: BID-003 | B13: Proposal Development | C13: 0 | D13: Jordan Ellis
... A241: BID-060 | B241: Proposal Development | C241: 0 | D241: Priya Shah

Sheet Lists
A1: Outcome | B1: Stage | C1: Service | D1: Market | E1: Owner | F1: Risk | G1: No-Bid Reason | H1: Client Type
A2: Won | B2: Initial Review | C2: Janitorial | D2: Metro NY | E2: Michael Ngo | F2: Low | G2: Geographic Distance | H2: Government
A3: Lost | B3: Operational Review | C3: Custodial | D3: North Jersey | E3: Avery Chen | F3: Medium | G3: Licensing Requirement | H3: Education
A4: Awaiting Award | B4: Pricing | C4: Facility Maintenance | D4: Hudson Valley | E4: Jordan Ellis | F4: High | G4: Scope Misalignment | H4: Commercial
A5: Submitted | B5: Proposal Development | C5: Pest Control | D5: Central Jersey | E5: Priya Shah | G5: Staffing / Operations Capacity
A6: No-Bid | B6: Submitted | C6: Landscaping | D6: Outer Region | G6: Insufficient Time
A7: In Progress | B7: Awaiting Award | C7: Security | G7: Minimum Qualifications
B8: Closed – Awarded | C8: Post-Construction Cleaning | G8: Pricing / Margin Concern
B9: Closed – No-Bid | C9: Specialty Floor Care
